{
"meta":{"test_sets":[],"test_metrics":[],"learn_metrics":[{"best_value":"Min","name":"RMSE"}],"launch_mode":"Train","parameters":"","iteration_count":1000,"learn_sets":["learn"],"name":"experiment"},
"iterations":[
{"learn":[14.59871775],"iteration":0,"passed_time":0.1222436677,"remaining_time":122.1214241},
{"learn":[14.22518863],"iteration":1,"passed_time":0.1231326624,"remaining_time":61.44319856},
{"learn":[13.8866124],"iteration":2,"passed_time":0.1241184888,"remaining_time":41.2487111},
{"learn":[13.52356875],"iteration":3,"passed_time":0.1249438466,"remaining_time":31.1110178},
{"learn":[13.18870211],"iteration":4,"passed_time":0.1264211741,"remaining_time":25.15781364},
{"learn":[12.9124226],"iteration":5,"passed_time":0.1274109813,"remaining_time":21.10775257},
{"learn":[12.60003351],"iteration":6,"passed_time":0.1284522339,"remaining_time":18.22186689},
{"learn":[12.32990573],"iteration":7,"passed_time":0.129578338,"remaining_time":16.06771391},
{"learn":[12.0660619],"iteration":8,"passed_time":0.1305294891,"remaining_time":14.37274708},
{"learn":[11.77309809],"iteration":9,"passed_time":0.1316563459,"remaining_time":13.03397825},
{"learn":[11.49227636],"iteration":10,"passed_time":0.1326277354,"remaining_time":11.92443912},
{"learn":[11.26264833],"iteration":11,"passed_time":0.1340763227,"remaining_time":11.03895057},
{"learn":[11.04260393],"iteration":12,"passed_time":0.135511795,"remaining_time":10.28847243},
{"learn":[10.79916926],"iteration":13,"passed_time":0.1365837274,"remaining_time":9.619396798},
{"learn":[10.5541002],"iteration":14,"passed_time":0.1387659205,"remaining_time":9.112295446},
{"learn":[10.31918115],"iteration":15,"passed_time":0.1397205116,"remaining_time":8.592811464},
{"learn":[10.10004441],"iteration":16,"passed_time":0.1406784729,"remaining_time":8.134525818},
{"learn":[9.894556723],"iteration":17,"passed_time":0.1417007549,"remaining_time":7.730563408},
{"learn":[9.690174082],"iteration":18,"passed_time":0.1426529412,"remaining_time":7.365396597},
{"learn":[9.506034866],"iteration":19,"passed_time":0.1438984703,"remaining_time":7.051025047},
{"learn":[9.338524633],"iteration":20,"passed_time":0.1450197652,"remaining_time":6.760683342},
{"learn":[9.170203312],"iteration":21,"passed_time":0.1458386813,"remaining_time":6.483192287},
{"learn":[9.010299969],"iteration":22,"passed_time":0.1466716125,"remaining_time":6.230355018},
{"learn":[8.843866678],"iteration":23,"passed_time":0.1475121657,"remaining_time":5.998828071},
{"learn":[8.690548059],"iteration":24,"passed_time":0.1483417877,"remaining_time":5.785329721},
{"learn":[8.555307687],"iteration":25,"passed_time":0.1493253704,"remaining_time":5.593958106},
{"learn":[8.413851302],"iteration":26,"passed_time":0.1504063018,"remaining_time":5.42019747},
{"learn":[8.29256019],"iteration":27,"passed_time":0.1515885135,"remaining_time":5.262286969},
{"learn":[8.162193833],"iteration":28,"passed_time":0.1532387768,"remaining_time":5.130856975},
{"learn":[8.040736294],"iteration":29,"passed_time":0.1543550747,"remaining_time":4.990814083},
{"learn":[7.921220278],"iteration":30,"passed_time":0.1554220916,"remaining_time":4.858193765},
{"learn":[7.809589039],"iteration":31,"passed_time":0.1566373334,"remaining_time":4.738279336},
{"learn":[7.699675801],"iteration":32,"passed_time":0.1575478386,"remaining_time":4.616629088},
{"learn":[7.60645267],"iteration":33,"passed_time":0.1584428593,"remaining_time":4.501641237},
{"learn":[7.498880302],"iteration":34,"passed_time":0.1594105072,"remaining_time":4.395175412},
{"learn":[7.401158744],"iteration":35,"passed_time":0.1603379565,"remaining_time":4.293494169},
{"learn":[7.306431077],"iteration":36,"passed_time":0.1612522992,"remaining_time":4.196917951},
{"learn":[7.223863468],"iteration":37,"passed_time":0.16235455,"remaining_time":4.110133609},
{"learn":[7.143477682],"iteration":38,"passed_time":0.1633564158,"remaining_time":4.02526963},
{"learn":[7.062817131],"iteration":39,"passed_time":0.1646664043,"remaining_time":3.951993703},
{"learn":[6.990793435],"iteration":40,"passed_time":0.1655599116,"remaining_time":3.872486714},
{"learn":[6.931862224],"iteration":41,"passed_time":0.1673309999,"remaining_time":3.816740425},
{"learn":[6.858296558],"iteration":42,"passed_time":0.1683700807,"remaining_time":3.747213191},
{"learn":[6.786268161],"iteration":43,"passed_time":0.1693511759,"remaining_time":3.679539185},
{"learn":[6.717118549],"iteration":44,"passed_time":0.1704879141,"remaining_time":3.6181324},
{"learn":[6.652948106],"iteration":45,"passed_time":0.1713075405,"remaining_time":3.552769427},
{"learn":[6.589686076],"iteration":46,"passed_time":0.1723268062,"remaining_time":3.494200986},
{"learn":[6.531283097],"iteration":47,"passed_time":0.1731828198,"remaining_time":3.434792592},
{"learn":[6.471368031],"iteration":48,"passed_time":0.1740711693,"remaining_time":3.378401674},
{"learn":[6.416481395],"iteration":49,"passed_time":0.1750304957,"remaining_time":3.325579419},
{"learn":[6.369870822],"iteration":50,"passed_time":0.1759564965,"remaining_time":3.274170887},
{"learn":[6.325678067],"iteration":51,"passed_time":0.176851494,"remaining_time":3.224138775},
{"learn":[6.275766122],"iteration":52,"passed_time":0.1777459081,"remaining_time":3.175950472},
{"learn":[6.224773967],"iteration":53,"passed_time":0.1787352717,"remaining_time":3.131177167},
{"learn":[6.182249254],"iteration":54,"passed_time":0.179556416,"remaining_time":3.085105693},
{"learn":[6.139904173],"iteration":55,"passed_time":0.1809452783,"remaining_time":3.050220405},
{"learn":[6.100525536],"iteration":56,"passed_time":0.1824794785,"remaining_time":3.018914881},
{"learn":[6.062568564],"iteration":57,"passed_time":0.1834768055,"remaining_time":2.979916393},
{"learn":[6.030559288],"iteration":58,"passed_time":0.1845409481,"remaining_time":2.943271731},
{"learn":[5.997931376],"iteration":59,"passed_time":0.1853354018,"remaining_time":2.903587962},
{"learn":[5.964103835],"iteration":60,"passed_time":0.1863278116,"remaining_time":2.868226476},
{"learn":[5.933729724],"iteration":61,"passed_time":0.1872659299,"remaining_time":2.833152295},
{"learn":[5.901932711],"iteration":62,"passed_time":0.1882701677,"remaining_time":2.800145193},
{"learn":[5.873727795],"iteration":63,"passed_time":0.1893182143,"remaining_time":2.768778885},
{"learn":[5.846485734],"iteration":64,"passed_time":0.1903920414,"remaining_time":2.738716288},
{"learn":[5.820630862],"iteration":65,"passed_time":0.1913744622,"remaining_time":2.708238601},
{"learn":[5.793646238],"iteration":66,"passed_time":0.1923541346,"remaining_time":2.678603098},
{"learn":[5.765388646],"iteration":67,"passed_time":0.1931421303,"remaining_time":2.647183316},
{"learn":[5.747073912],"iteration":68,"passed_time":0.1941554112,"remaining_time":2.619691128},
{"learn":[5.722315217],"iteration":69,"passed_time":0.1953986252,"remaining_time":2.596010306},
{"learn":[5.699970599],"iteration":70,"passed_time":0.1967546463,"remaining_time":2.574437555},
{"learn":[5.682732647],"iteration":71,"passed_time":0.1978851966,"remaining_time":2.550520311},
{"learn":[5.663525791],"iteration":72,"passed_time":0.1990440617,"remaining_time":2.527586921},
{"learn":[5.642381613],"iteration":73,"passed_time":0.1999162634,"remaining_time":2.501654864},
{"learn":[5.621404779],"iteration":74,"passed_time":0.2008579793,"remaining_time":2.477248411},
{"learn":[5.602460129],"iteration":75,"passed_time":0.2017737327,"remaining_time":2.453143803},
{"learn":[5.587337574],"iteration":76,"passed_time":0.2029589561,"remaining_time":2.432871643},
{"learn":[5.572393026],"iteration":77,"passed_time":0.2039027038,"remaining_time":2.410234524},
{"learn":[5.558425806],"iteration":78,"passed_time":0.2047534034,"remaining_time":2.387061829},
{"learn":[5.541518902],"iteration":79,"passed_time":0.2055730418,"remaining_time":2.364089981},
{"learn":[5.526157283],"iteration":80,"passed_time":0.2064038095,"remaining_time":2.34179137},
{"learn":[5.511746977],"iteration":81,"passed_time":0.2072614374,"remaining_time":2.320317067},
{"learn":[5.504975022],"iteration":82,"passed_time":0.2077670222,"remaining_time":2.295450113},
{"learn":[5.493980522],"iteration":83,"passed_time":0.2085716041,"remaining_time":2.274423683},
{"learn":[5.480745463],"iteration":84,"passed_time":0.2098948953,"remaining_time":2.259456815},
{"learn":[5.464052013],"iteration":85,"passed_time":0.2108870712,"remaining_time":2.241288176},
{"learn":[5.449143727],"iteration":86,"passed_time":0.2121907181,"remaining_time":2.226783053},
{"learn":[5.438255432],"iteration":87,"passed_time":0.2133753512,"remaining_time":2.211344549},
{"learn":[5.425927931],"iteration":88,"passed_time":0.2144188561,"remaining_time":2.194781775},
{"learn":[5.412331217],"iteration":89,"passed_time":0.2152253846,"remaining_time":2.176167778},
{"learn":[5.400691499],"iteration":90,"passed_time":0.2161141401,"remaining_time":2.15876652},
{"learn":[5.391618744],"iteration":91,"passed_time":0.2169648064,"remaining_time":2.141348307},
{"learn":[5.380766572],"iteration":92,"passed_time":0.2178515355,"remaining_time":2.124638093},
{"learn":[5.372207183],"iteration":93,"passed_time":0.2186706987,"remaining_time":2.10761333},
{"learn":[5.362918837],"iteration":94,"passed_time":0.2194704576,"remaining_time":2.090744886},
{"learn":[5.348292324],"iteration":95,"passed_time":0.2204104828,"remaining_time":2.075532046},
{"learn":[5.339772295],"iteration":96,"passed_time":0.2212422716,"remaining_time":2.059605889},
{"learn":[5.331515983],"iteration":97,"passed_time":0.2220556369,"remaining_time":2.043818209},
{"learn":[5.323861644],"iteration":98,"passed_time":0.2229826609,"remaining_time":2.029367449},
{"learn":[5.313277281],"iteration":99,"passed_time":0.2237677674,"remaining_time":2.013909907},
{"learn":[5.30685627],"iteration":100,"passed_time":0.2245924045,"remaining_time":1.999094769},
{"learn":[5.29652059],"iteration":101,"passed_time":0.2255304593,"remaining_time":1.985552475},
{"learn":[5.288350766],"iteration":102,"passed_time":0.2267350276,"remaining_time":1.97457592},
{"learn":[5.27993346],"iteration":103,"passed_time":0.2276857928,"remaining_time":1.961600677},
{"learn":[5.271789139],"iteration":104,"passed_time":0.2285728376,"remaining_time":1.94831133},
{"learn":[5.262684686],"iteration":105,"passed_time":0.2294279289,"remaining_time":1.934986495},
{"learn":[5.251619772],"iteration":106,"passed_time":0.2302626406,"remaining_time":1.921724655},
{"learn":[5.241012171],"iteration":107,"passed_time":0.2310666114,"remaining_time":1.908439049},
{"learn":[5.232684032],"iteration":108,"passed_time":0.2319849869,"remaining_time":1.896317645},
{"learn":[5.224267141],"iteration":109,"passed_time":0.2329687789,"remaining_time":1.884929211},
{"learn":[5.216324968],"iteration":110,"passed_time":0.233802816,"remaining_time":1.872528859},
{"learn":[5.211102527],"iteration":111,"passed_time":0.2344665679,"remaining_time":1.858984931},
{"learn":[5.206364257],"iteration":112,"passed_time":0.2350768199,"remaining_time":1.84524902},
{"learn":[5.196937641],"iteration":113,"passed_time":0.2357213678,"remaining_time":1.832009929},
{"learn":[5.190746047],"iteration":114,"passed_time":0.2363287609,"remaining_time":1.818703942},
{"learn":[5.181885213],"iteration":115,"passed_time":0.2369541878,"remaining_time":1.805754328},
{"learn":[5.178293568],"iteration":116,"passed_time":0.237475577,"remaining_time":1.792230209},
{"learn":[5.170991438],"iteration":117,"passed_time":0.2380991981,"remaining_time":1.779690617},
{"learn":[5.166257212],"iteration":118,"passed_time":0.2387269539,"remaining_time":1.767381902},
{"learn":[5.161421246],"iteration":119,"passed_time":0.2393157552,"remaining_time":1.754982205},
{"learn":[5.158223542],"iteration":120,"passed_time":0.2399116958,"remaining_time":1.742829592},
{"learn":[5.15470988],"iteration":121,"passed_time":0.2406582713,"remaining_time":1.73195051},
{"learn":[5.146388143],"iteration":122,"passed_time":0.2419249498,"remaining_time":1.724944561},
{"learn":[5.139529364],"iteration":123,"passed_time":0.2428258232,"remaining_time":1.715446945},
{"learn":[5.134276023],"iteration":124,"passed_time":0.2435593996,"remaining_time":1.704915797},
{"learn":[5.128536065],"iteration":125,"passed_time":0.2442453832,"remaining_time":1.694210039},
{"learn":[5.123300353],"iteration":126,"passed_time":0.2448030677,"remaining_time":1.682780143},
{"learn":[5.116200518],"iteration":127,"passed_time":0.2456379555,"remaining_time":1.673408572},
{"learn":[5.108728704],"iteration":128,"passed_time":0.2463454736,"remaining_time":1.66330936},
{"learn":[5.104075866],"iteration":129,"passed_time":0.2469513616,"remaining_time":1.652674497},
{"learn":[5.100317606],"iteration":130,"passed_time":0.2475794301,"remaining_time":1.642339884},
{"learn":[5.095814182],"iteration":131,"passed_time":0.2481962747,"remaining_time":1.632078533},
{"learn":[5.092146915],"iteration":132,"passed_time":0.2489514284,"remaining_time":1.622863823},
{"learn":[5.085258329],"iteration":133,"passed_time":0.2496554894,"remaining_time":1.613445178},
{"learn":[5.079219421],"iteration":134,"passed_time":0.2503300404,"remaining_time":1.603966555},
{"learn":[5.076476829],"iteration":135,"passed_time":0.2509261256,"remaining_time":1.594118915},
{"learn":[5.072133867],"iteration":136,"passed_time":0.2516683587,"remaining_time":1.58532696},
{"learn":[5.067031564],"iteration":137,"passed_time":0.2522995021,"remaining_time":1.57595776},
{"learn":[5.061358312],"iteration":138,"passed_time":0.2529758726,"remaining_time":1.566994434},
{"learn":[5.056759124],"iteration":139,"passed_time":0.2536170611,"remaining_time":1.557933375},
{"learn":[5.050254],"iteration":140,"passed_time":0.2542176738,"remaining_time":1.548744552},
{"learn":[5.048376474],"iteration":141,"passed_time":0.2546171352,"remaining_time":1.538461282},
{"learn":[5.042603751],"iteration":142,"passed_time":0.2552566853,"remaining_time":1.5297551},
{"learn":[5.037477349],"iteration":143,"passed_time":0.2561332426,"remaining_time":1.522569831},
{"learn":[5.03230489],"iteration":144,"passed_time":0.2571666289,"remaining_time":1.516396329},
{"learn":[5.025976187],"iteration":145,"passed_time":0.2578243329,"remaining_time":1.508095756},
{"learn":[5.01952451],"iteration":146,"passed_time":0.2584511291,"remaining_time":1.499719817},
{"learn":[5.017569424],"iteration":147,"passed_time":0.259216931,"remaining_time":1.492248819},
{"learn":[5.008962367],"iteration":148,"passed_time":0.2598991933,"remaining_time":1.484390695},
{"learn":[5.003880266],"iteration":149,"passed_time":0.2606070674,"remaining_time":1.476773382},
{"learn":[4.996387564],"iteration":150,"passed_time":0.2612779615,"remaining_time":1.469039664},
{"learn":[4.993361683],"iteration":151,"passed_time":0.2619603642,"remaining_time":1.461463084},
{"learn":[4.99005752],"iteration":152,"passed_time":0.2626119068,"remaining_time":1.453805785},
{"learn":[4.986908764],"iteration":153,"passed_time":0.2632430481,"remaining_time":1.446127394},
{"learn":[4.985207175],"iteration":154,"passed_time":0.2638683924,"remaining_time":1.438508333},
{"learn":[4.979003494],"iteration":155,"passed_time":0.2645654815,"remaining_time":1.431367092},
{"learn":[4.973142217],"iteration":156,"passed_time":0.2651951498,"remaining_time":1.423945932},
{"learn":[4.967056696],"iteration":157,"passed_time":0.2659003407,"remaining_time":1.417013208},
{"learn":[4.961460696],"iteration":158,"passed_time":0.2665320715,"remaining_time":1.409770265},
{"learn":[4.954240363],"iteration":159,"passed_time":0.2671580605,"remaining_time":1.402579818},
{"learn":[4.952320707],"iteration":160,"passed_time":0.2675977291,"remaining_time":1.394499967},
{"learn":[4.948337777],"iteration":161,"passed_time":0.268290152,"remaining_time":1.387821897},
{"learn":[4.943228639],"iteration":162,"passed_time":0.268908944,"remaining_time":1.380839178},
{"learn":[4.938545759],"iteration":163,"passed_time":0.269705638,"remaining_time":1.374840935},
{"learn":[4.935330572],"iteration":164,"passed_time":0.270529195,"remaining_time":1.369041684},
{"learn":[4.932051543],"iteration":165,"passed_time":0.2721995601,"remaining_time":1.367556826},
{"learn":[4.928964153],"iteration":166,"passed_time":0.2729440576,"remaining_time":1.361451497},
{"learn":[4.922860227],"iteration":167,"passed_time":0.2736884219,"remaining_time":1.355409327},
{"learn":[4.917668772],"iteration":168,"passed_time":0.2745798742,"remaining_time":1.350153109},
{"learn":[4.910365386],"iteration":169,"passed_time":0.2753131951,"remaining_time":1.344176188},
{"learn":[4.906457206],"iteration":170,"passed_time":0.2759302951,"remaining_time":1.337697162},
{"learn":[4.901996508],"iteration":171,"passed_time":0.2765577077,"remaining_time":1.331335942},
{"learn":[4.896816173],"iteration":172,"passed_time":0.2771465402,"remaining_time":1.324856582},
{"learn":[4.891123132],"iteration":173,"passed_time":0.2777631828,"remaining_time":1.318576948},
{"learn":[4.887630202],"iteration":174,"passed_time":0.2783658215,"remaining_time":1.312296016},
{"learn":[4.885259712],"iteration":175,"passed_time":0.2789777451,"remaining_time":1.306123079},
{"learn":[4.880659728],"iteration":176,"passed_time":0.2795741389,"remaining_time":1.29994077},
{"learn":[4.877299723],"iteration":177,"passed_time":0.2801846484,"remaining_time":1.29388641},
{"learn":[4.874038772],"iteration":178,"passed_time":0.2808859478,"remaining_time":1.288309291},
{"learn":[4.86943698],"iteration":179,"passed_time":0.2814854347,"remaining_time":1.282322536},
{"learn":[4.861268711],"iteration":180,"passed_time":0.2821317274,"remaining_time":1.276607098},
{"learn":[4.858673056],"iteration":181,"passed_time":0.2827271637,"remaining_time":1.270718791},
{"learn":[4.854036207],"iteration":182,"passed_time":0.283362914,"remaining_time":1.26506831},
{"learn":[4.85130244],"iteration":183,"passed_time":0.2840556035,"remaining_time":1.25972485},
{"learn":[4.847510084],"iteration":184,"passed_time":0.2846984682,"remaining_time":1.254212171},
{"learn":[4.845691673],"iteration":185,"passed_time":0.285330518,"remaining_time":1.248704525},
{"learn":[4.842058646],"iteration":186,"passed_time":0.2864311533,"remaining_time":1.245286244},
{"learn":[4.838623675],"iteration":187,"passed_time":0.2877052801,"remaining_time":1.242641955},
{"learn":[4.834602161],"iteration":188,"passed_time":0.288418631,"remaining_time":1.237605872},
{"learn":[4.830858976],"iteration":189,"passed_time":0.2890466787,"remaining_time":1.23225163},
{"learn":[4.827590511],"iteration":190,"passed_time":0.2896865092,"remaining_time":1.226996785},
{"learn":[4.822246226],"iteration":191,"passed_time":0.290315181,"remaining_time":1.221743053},
{"learn":[4.816686395],"iteration":192,"passed_time":0.2909124733,"remaining_time":1.216406041},
{"learn":[4.814797121],"iteration":193,"passed_time":0.2915269093,"remaining_time":1.211189118},
{"learn":[4.811639392],"iteration":194,"passed_time":0.2922262512,"remaining_time":1.206369909},
{"learn":[4.804813432],"iteration":195,"passed_time":0.2928886547,"remaining_time":1.201441216},
{"learn":[4.80251613],"iteration":196,"passed_time":0.2936187728,"remaining_time":1.196831851},
{"learn":[4.800087884],"iteration":197,"passed_time":0.2942504218,"remaining_time":1.19186282},
{"learn":[4.794773135],"iteration":198,"passed_time":0.29494991,"remaining_time":1.187210442},
{"learn":[4.791664833],"iteration":199,"passed_time":0.2955401561,"remaining_time":1.182160624},
{"learn":[4.785989873],"iteration":200,"passed_time":0.2961804037,"remaining_time":1.177353943},
{"learn":[4.782387142],"iteration":201,"passed_time":0.2967935033,"remaining_time":1.172481265},
{"learn":[4.778623704],"iteration":202,"passed_time":0.2974362375,"remaining_time":1.167766903},
{"learn":[4.775772178],"iteration":203,"passed_time":0.2981051115,"remaining_time":1.163194455},
{"learn":[4.77023101],"iteration":204,"passed_time":0.2987028006,"remaining_time":1.158384031},
{"learn":[4.764496689],"iteration":205,"passed_time":0.2993281008,"remaining_time":1.153720932},
{"learn":[4.763138716],"iteration":206,"passed_time":0.2999212249,"remaining_time":1.148973581},
{"learn":[4.758053283],"iteration":207,"passed_time":0.3005891085,"remaining_time":1.144550836},
{"learn":[4.755063788],"iteration":208,"passed_time":0.3014516349,"remaining_time":1.140900685},
{"learn":[4.752465267],"iteration":209,"passed_time":0.3025620934,"remaining_time":1.13820978},
{"learn":[4.748067377],"iteration":210,"passed_time":0.3032076703,"remaining_time":1.133795506},
{"learn":[4.744163298],"iteration":211,"passed_time":0.3038165264,"remaining_time":1.129280296},
{"learn":[4.736670896],"iteration":212,"passed_time":0.304464558,"remaining_time":1.124946512},
{"learn":[4.73349255],"iteration":213,"passed_time":0.3050828394,"remaining_time":1.120537906},
{"learn":[4.731864595],"iteration":214,"passed_time":0.3056891013,"remaining_time":1.116120672},
{"learn":[4.728398311],"iteration":215,"passed_time":0.3063248479,"remaining_time":1.111845744},
{"learn":[4.723865975],"iteration":216,"passed_time":0.3069709453,"remaining_time":1.107641706},
{"learn":[4.723483365],"iteration":217,"passed_time":0.3075264315,"remaining_time":1.103145273},
{"learn":[4.72095416],"iteration":218,"passed_time":0.3081033816,"remaining_time":1.098761374},
{"learn":[4.716173382],"iteration":219,"passed_time":0.3087402639,"remaining_time":1.094624572},
{"learn":[4.710563974],"iteration":220,"passed_time":0.3093483681,"remaining_time":1.090418004},
{"learn":[4.707160263],"iteration":221,"passed_time":0.309984946,"remaining_time":1.086343639},
{"learn":[4.70408351],"iteration":222,"passed_time":0.3105811051,"remaining_time":1.082159276},
{"learn":[4.702501831],"iteration":223,"passed_time":0.3112624024,"remaining_time":1.078301894},
{"learn":[4.700269738],"iteration":224,"passed_time":0.3120741202,"remaining_time":1.074921969},
{"learn":[4.695346302],"iteration":225,"passed_time":0.3129315557,"remaining_time":1.071721345},
{"learn":[4.689769299],"iteration":226,"passed_time":0.3137741647,"remaining_time":1.068490878},
{"learn":[4.687919514],"iteration":227,"passed_time":0.3144872572,"remaining_time":1.064842818},
{"learn":[4.682982074],"iteration":228,"passed_time":0.3154417926,"remaining_time":1.062033284},
{"learn":[4.679578702],"iteration":229,"passed_time":0.3161936318,"remaining_time":1.058561289},
{"learn":[4.675751423],"iteration":230,"passed_time":0.3169550141,"remaining_time":1.055144614},
{"learn":[4.672710726],"iteration":231,"passed_time":0.3180697522,"remaining_time":1.052920559},
{"learn":[4.6690533],"iteration":232,"passed_time":0.3187268364,"remaining_time":1.0491995},
{"learn":[4.667595702],"iteration":233,"passed_time":0.319356594,"remaining_time":1.045415175},
{"learn":[4.664241291],"iteration":234,"passed_time":0.3199471567,"remaining_time":1.041530106},
{"learn":[4.662246999],"iteration":235,"passed_time":0.3205669743,"remaining_time":1.037767663},
{"learn":[4.658668443],"iteration":236,"passed_time":0.3211928632,"remaining_time":1.034051285},
{"learn":[4.658017572],"iteration":237,"passed_time":0.3218748791,"remaining_time":1.030540579},
{"learn":[4.657656705],"iteration":238,"passed_time":0.3224417231,"remaining_time":1.026686825},
{"learn":[4.653242871],"iteration":239,"passed_time":0.3231157963,"remaining_time":1.023200022},
{"learn":[4.6507302],"iteration":240,"passed_time":0.3237555832,"remaining_time":1.019628579},
{"learn":[4.647671336],"iteration":241,"passed_time":0.3243832517,"remaining_time":1.016043408},
{"learn":[4.645506007],"iteration":242,"passed_time":0.3250222044,"remaining_time":1.012517731},
{"learn":[4.641297906],"iteration":243,"passed_time":0.3257177296,"remaining_time":1.009190998},
{"learn":[4.63798107],"iteration":244,"passed_time":0.3265914276,"remaining_time":1.006434807},
{"learn":[4.635062318],"iteration":245,"passed_time":0.3272353183,"remaining_time":1.002989553},
{"learn":[4.631606017],"iteration":246,"passed_time":0.327905021,"remaining_time":0.9996456714},
{"learn":[4.630215494],"iteration":247,"passed_time":0.3285690808,"remaining_time":0.9963062451},
{"learn":[4.62729814],"iteration":248,"passed_time":0.3292457687,"remaining_time":0.9930263947},
{"learn":[4.624691756],"iteration":249,"passed_time":0.3299124614,"remaining_time":0.9897373841},
{"learn":[4.621840053],"iteration":250,"passed_time":0.3305726769,"remaining_time":0.9864499403},
{"learn":[4.619602091],"iteration":251,"passed_time":0.3311828641,"remaining_time":0.9830348505},
{"learn":[4.613584029],"iteration":252,"passed_time":0.3322602516,"remaining_time":0.9810213754},
{"learn":[4.6119388],"iteration":253,"passed_time":0.3330370653,"remaining_time":0.9781324832},
{"learn":[4.60870702],"iteration":254,"passed_time":0.3336778222,"remaining_time":0.974862657},
{"learn":[4.604771557],"iteration":255,"passed_time":0.3342700773,"remaining_time":0.971472412},
{"learn":[4.604231277],"iteration":256,"passed_time":0.3353115778,"remaining_time":0.9694027328},
{"learn":[4.600750354],"iteration":257,"passed_time":0.3360244323,"remaining_time":0.9663958479},
{"learn":[4.596488253],"iteration":258,"passed_time":0.3366935588,"remaining_time":0.9632815718},
{"learn":[4.59470784],"iteration":259,"passed_time":0.3373583892,"remaining_time":0.960173877},
{"learn":[4.588818005],"iteration":260,"passed_time":0.3379571908,"remaining_time":0.9568979462},
{"learn":[4.585054174],"iteration":261,"passed_time":0.3385680667,"remaining_time":0.9536764626},
{"learn":[4.581471435],"iteration":262,"passed_time":0.3391797426,"remaining_time":0.9504770735},
{"learn":[4.577555199],"iteration":263,"passed_time":0.3397900748,"remaining_time":0.9472935417},
{"learn":[4.57457145],"iteration":264,"passed_time":0.3404407346,"remaining_time":0.9442412828},
{"learn":[4.573029224],"iteration":265,"passed_time":0.3410688646,"remaining_time":0.9411449122},
{"learn":[4.571326203],"iteration":266,"passed_time":0.3416910555,"remaining_time":0.9380507254},
{"learn":[4.571019224],"iteration":267,"passed_time":0.3423191415,"remaining_time":0.9349910879},
{"learn":[4.565766631],"iteration":268,"passed_time":0.3430852691,"remaining_time":0.9323246532},
{"learn":[4.563383471],"iteration":269,"passed_time":0.343856223,"remaining_time":0.9296853437},
{"learn":[4.558165805],"iteration":270,"passed_time":0.3444917257,"remaining_time":0.9266954541},
{"learn":[4.55629209],"iteration":271,"passed_time":0.3451738032,"remaining_time":0.923847532},
{"learn":[4.549383848],"iteration":272,"passed_time":0.3458941192,"remaining_time":0.9211173065},
{"learn":[4.546227503],"iteration":273,"passed_time":0.346525435,"remaining_time":0.9181659337},
{"learn":[4.540620977],"iteration":274,"passed_time":0.3475649022,"remaining_time":0.9163074693},
{"learn":[4.532898237],"iteration":275,"passed_time":0.3483507573,"remaining_time":0.9137896676},
{"learn":[4.529757367],"iteration":276,"passed_time":0.3489775019,"remaining_time":0.9108690753},
{"learn":[4.52579294],"iteration":277,"passed_time":0.3496672005,"remaining_time":0.9081284846},
{"learn":[4.521572155],"iteration":278,"passed_time":0.3503011429,"remaining_time":0.9052585091},
{"learn":[4.518818099],"iteration":279,"passed_time":0.3509753662,"remaining_time":0.9025080844},
{"learn":[4.514012334],"iteration":280,"passed_time":0.3516456866,"remaining_time":0.8997624508},
{"learn":[4.508331416],"iteration":281,"passed_time":0.35228206,"remaining_time":0.8969451032},
{"learn":[4.506038537],"iteration":282,"passed_time":0.3529682637,"remaining_time":0.8942694173},
{"learn":[4.505805643],"iteration":283,"passed_time":0.3536014788,"remaining_time":0.8914741508},
{"learn":[4.501550352],"iteration":284,"passed_time":0.3543086421,"remaining_time":0.8888795758},
{"learn":[4.494692643],"iteration":285,"passed_time":0.3550472051,"remaining_time":0.886376589},
{"learn":[4.489330245],"iteration":286,"passed_time":0.355713128,"remaining_time":0.8837054365},
{"learn":[4.484826955],"iteration":287,"passed_time":0.3563367026,"remaining_time":0.8809435148},
{"learn":[4.478285428],"iteration":288,"passed_time":0.3570011899,"remaining_time":0.878297045},
{"learn":[4.475311671],"iteration":289,"passed_time":0.3576866575,"remaining_time":0.8757156097},
{"learn":[4.471581298],"iteration":290,"passed_time":0.358414996,"remaining_time":0.8732516568},
{"learn":[4.469164956],"iteration":291,"passed_time":0.3590922052,"remaining_time":0.8706756208},
{"learn":[4.462068024],"iteration":292,"passed_time":0.3597729844,"remaining_time":0.8681211604},
{"learn":[4.458540976],"iteration":293,"passed_time":0.3603786295,"remaining_time":0.8653990218},
{"learn":[4.455757458],"iteration":294,"passed_time":0.3610071375,"remaining_time":0.862745871},
{"learn":[4.453027414],"iteration":295,"passed_time":0.3618772206,"remaining_time":0.8606809572},
{"learn":[4.450659338],"iteration":296,"passed_time":0.3630647712,"remaining_time":0.8593755358},
{"learn":[4.444696901],"iteration":297,"passed_time":0.3638190558,"remaining_time":0.8570502591},
{"learn":[4.442052813],"iteration":298,"passed_time":0.3644918779,"remaining_time":0.854544503},
{"learn":[4.440036756],"iteration":299,"passed_time":0.3651809359,"remaining_time":0.8520888504},
{"learn":[4.435017051],"iteration":300,"passed_time":0.3658797905,"remaining_time":0.8496676864},
{"learn":[4.429962125],"iteration":301,"passed_time":0.3665048743,"remaining_time":0.8470874248},
{"learn":[4.427666256],"iteration":302,"passed_time":0.3671014983,"remaining_time":0.8444546017},
{"learn":[4.425030004],"iteration":303,"passed_time":0.367718774,"remaining_time":0.8418824563},
{"learn":[4.422588771],"iteration":304,"passed_time":0.3683830743,"remaining_time":0.8394302842},
{"learn":[4.418936667],"iteration":305,"passed_time":0.3690025376,"remaining_time":0.8368881082},
{"learn":[4.416887976],"iteration":306,"passed_time":0.3696038478,"remaining_time":0.8343174806},
{"learn":[4.413773354],"iteration":307,"passed_time":0.3701921902,"remaining_time":0.8317305051},
{"learn":[4.411129391],"iteration":308,"passed_time":0.3708590972,"remaining_time":0.8293321558},
{"learn":[4.40850819],"iteration":309,"passed_time":0.3715165444,"remaining_time":0.8269239215},
{"learn":[4.404880292],"iteration":310,"passed_time":0.3721850047,"remaining_time":0.8245513447},
{"learn":[4.404593827],"iteration":311,"passed_time":0.3727938542,"remaining_time":0.8220582426},
{"learn":[4.402139942],"iteration":312,"passed_time":0.373387974,"remaining_time":0.8195448504},
{"learn":[4.400284725],"iteration":313,"passed_time":0.373999174,"remaining_time":0.8170809979},
{"learn":[4.395805521],"iteration":314,"passed_time":0.3746382663,"remaining_time":0.8146895632},
{"learn":[4.392838833],"iteration":315,"passed_time":0.3752715112,"remaining_time":0.8122965623},
{"learn":[4.389213061],"iteration":316,"passed_time":0.3758720887,"remaining_time":0.8098442794},
{"learn":[4.3861981],"iteration":317,"passed_time":0.3765078876,"remaining_time":0.8074791803},
{"learn":[4.385054234],"iteration":318,"passed_time":0.3772392976,"remaining_time":0.8053290335},
{"learn":[4.379364607],"iteration":319,"passed_time":0.3784271967,"remaining_time":0.804157793},
{"learn":[4.378387619],"iteration":320,"passed_time":0.3792751438,"remaining_time":0.8022673602},
{"learn":[4.375816727],"iteration":321,"passed_time":0.3799980238,"remaining_time":0.8001200625},
{"learn":[4.374600202],"iteration":322,"passed_time":0.3806228733,"remaining_time":0.7977761152},
{"learn":[4.37098897],"iteration":323,"passed_time":0.3812636011,"remaining_time":0.7954759084},
{"learn":[4.367418484],"iteration":324,"passed_time":0.3819381458,"remaining_time":0.793256149},
{"learn":[4.363584638],"iteration":325,"passed_time":0.3826434809,"remaining_time":0.791109528},
{"learn":[4.360770706],"iteration":326,"passed_time":0.3832953808,"remaining_time":0.7888617469},
{"learn":[4.358675808],"iteration":327,"passed_time":0.3839407429,"remaining_time":0.7866103025},
{"learn":[4.354228195],"iteration":328,"passed_time":0.3847333891,"remaining_time":0.7846690094},
{"learn":[4.353773425],"iteration":329,"passed_time":0.3854106856,"remaining_time":0.7825004828},
{"learn":[4.351648009],"iteration":330,"passed_time":0.3861858164,"remaining_time":0.7805387045},
{"learn":[4.348209927],"iteration":331,"passed_time":0.3869445954,"remaining_time":0.7785511739},
{"learn":[4.345852733],"iteration":332,"passed_time":0.3876103281,"remaining_time":0.7763846511},
{"learn":[4.34237339],"iteration":333,"passed_time":0.388305174,"remaining_time":0.7742851673},
{"learn":[4.340814362],"iteration":334,"passed_time":0.38898387,"remaining_time":0.7721620106},
{"learn":[4.339707068],"iteration":335,"passed_time":0.389616427,"remaining_time":0.7699562725},
{"learn":[4.335430786],"iteration":336,"passed_time":0.3903557988,"remaining_time":0.7679700138},
{"learn":[4.33521887],"iteration":337,"passed_time":0.391030563,"remaining_time":0.7658645937},
{"learn":[4.328507238],"iteration":338,"passed_time":0.391638116,"remaining_time":0.7636365624},
{"learn":[4.326140732],"iteration":339,"passed_time":0.3924878344,"remaining_time":0.7618881491},
{"learn":[4.323785636],"iteration":340,"passed_time":0.3936539858,"remaining_time":0.7607565298},
{"learn":[4.320632534],"iteration":341,"passed_time":0.394443082,"remaining_time":0.758899263},
{"learn":[4.31973724],"iteration":342,"passed_time":0.3951255246,"remaining_time":0.7568439348},
{"learn":[4.318000924],"iteration":343,"passed_time":0.3958036282,"remaining_time":0.7547883142},
{"learn":[4.312713628],"iteration":344,"passed_time":0.3965829181,"remaining_time":0.7529327865},
{"learn":[4.308220789],"iteration":345,"passed_time":0.3973293897,"remaining_time":0.7510214476},
{"learn":[4.305890947],"iteration":346,"passed_time":0.3980261025,"remaining_time":0.7490231842},
{"learn":[4.305137856],"iteration":347,"passed_time":0.3987399788,"remaining_time":0.7470645581},
{"learn":[4.304787172],"iteration":348,"passed_time":0.3997654088,"remaining_time":0.7456942153},
{"learn":[4.30350134],"iteration":349,"passed_time":0.4007196107,"remaining_time":0.7441935627},
{"learn":[4.30293809],"iteration":350,"passed_time":0.4013751147,"remaining_time":0.7421437305},
{"learn":[4.299548459],"iteration":351,"passed_time":0.4021017641,"remaining_time":0.740232793},
{"learn":[4.294768408],"iteration":352,"passed_time":0.4028355681,"remaining_time":0.7383416787},
{"learn":[4.294581479],"iteration":353,"passed_time":0.4034403375,"remaining_time":0.7362216328},
{"learn":[4.292551604],"iteration":354,"passed_time":0.4041074543,"remaining_time":0.7342234028},
{"learn":[4.288628894],"iteration":355,"passed_time":0.40488827,"remaining_time":0.7324383312},
{"learn":[4.287802767],"iteration":356,"passed_time":0.4056212457,"remaining_time":0.7305727199},
{"learn":[4.284566905],"iteration":357,"passed_time":0.406335223,"remaining_time":0.7286793664},
{"learn":[4.27890232],"iteration":358,"passed_time":0.4071064586,"remaining_time":0.7268948188},
{"learn":[4.276938023],"iteration":359,"passed_time":0.4080044004,"remaining_time":0.7253411563},
{"learn":[4.273425094],"iteration":360,"passed_time":0.4090524911,"remaining_time":0.7240569025},
{"learn":[4.269726505],"iteration":361,"passed_time":0.4098974751,"remaining_time":0.7224159919},
{"learn":[4.265565857],"iteration":362,"passed_time":0.4105785821,"remaining_time":0.720491892},
{"learn":[4.262117173],"iteration":363,"passed_time":0.4112482412,"remaining_time":0.7185546192},
{"learn":[4.259185148],"iteration":364,"passed_time":0.4118970188,"remaining_time":0.7165879643},
{"learn":[4.257668507],"iteration":365,"passed_time":0.4125596974,"remaining_time":0.7146525905},
{"learn":[4.253432436],"iteration":366,"passed_time":0.4133084209,"remaining_time":0.7128725625},
{"learn":[4.250216667],"iteration":367,"passed_time":0.4139826151,"remaining_time":0.7109701433},
{"learn":[4.24514828],"iteration":368,"passed_time":0.4146025166,"remaining_time":0.7089815393},
{"learn":[4.244015772],"iteration":369,"passed_time":0.4151921367,"remaining_time":0.7069487734},
{"learn":[4.240329192],"iteration":370,"passed_time":0.4158087358,"remaining_time":0.7049695277},
{"learn":[4.236718014],"iteration":371,"passed_time":0.416401486,"remaining_time":0.7029573473},
{"learn":[4.233495944],"iteration":372,"passed_time":0.4170066799,"remaining_time":0.7009736952},
{"learn":[4.230357491],"iteration":373,"passed_time":0.4176114472,"remaining_time":0.6989967004},
{"learn":[4.227381215],"iteration":374,"passed_time":0.4182006174,"remaining_time":0.697001029},
{"learn":[4.226169067],"iteration":375,"passed_time":0.418801344,"remaining_time":0.6950320177},
{"learn":[4.225963861],"iteration":376,"passed_time":0.419380666,"remaining_time":0.6930348937},
{"learn":[4.224346548],"iteration":377,"passed_time":0.4199868902,"remaining_time":0.6910895388},
{"learn":[4.222595381],"iteration":378,"passed_time":0.42065535,"remaining_time":0.6892532252},
{"learn":[4.219700938],"iteration":379,"passed_time":0.4212771915,"remaining_time":0.6873469966},
{"learn":[4.216356207],"iteration":380,"passed_time":0.4219742395,"remaining_time":0.6855696962},
{"learn":[4.214326494],"iteration":381,"passed_time":0.4229473031,"remaining_time":0.6842445899},
{"learn":[4.212901398],"iteration":382,"passed_time":0.4243210208,"remaining_time":0.6835667619},
{"learn":[4.211331091],"iteration":383,"passed_time":0.4251720701,"remaining_time":0.6820468625},
{"learn":[4.208624791],"iteration":384,"passed_time":0.4258924464,"remaining_time":0.6803217001},
{"learn":[4.204659106],"iteration":385,"passed_time":0.4266643051,"remaining_time":0.6786836355},
{"learn":[4.202968852],"iteration":386,"passed_time":0.4273746454,"remaining_time":0.6769526038},
{"learn":[4.197261935],"iteration":387,"passed_time":0.4282232252,"remaining_time":0.675444881},
{"learn":[4.196934403],"iteration":388,"passed_time":0.4289735888,"remaining_time":0.6737862796},
{"learn":[4.192479929],"iteration":389,"passed_time":0.4296982276,"remaining_time":0.6720920996},
{"learn":[4.190243116],"iteration":390,"passed_time":0.4305371075,"remaining_time":0.6705808145},
{"learn":[4.185852431],"iteration":391,"passed_time":0.4313062436,"remaining_time":0.6689647859},
{"learn":[4.180967944],"iteration":392,"passed_time":0.4320127435,"remaining_time":0.6672563239},
{"learn":[4.178283162],"iteration":393,"passed_time":0.4327490175,"remaining_time":0.6655987427},
{"learn":[4.176341157],"iteration":394,"passed_time":0.4334170881,"remaining_time":0.6638413628},
{"learn":[4.176041504],"iteration":395,"passed_time":0.4340978682,"remaining_time":0.6621088697},
{"learn":[4.175564513],"iteration":396,"passed_time":0.4349570318,"remaining_time":0.6606526201},
{"learn":[4.170830274],"iteration":397,"passed_time":0.4357791137,"remaining_time":0.6591432826},
{"learn":[4.167804808],"iteration":398,"passed_time":0.4365140211,"remaining_time":0.6575060819},
{"learn":[4.165860548],"iteration":399,"passed_time":0.4372892359,"remaining_time":0.6559338538},
{"learn":[4.160950571],"iteration":400,"passed_time":0.4382321635,"remaining_time":0.6546161245},
{"learn":[4.158544115],"iteration":401,"passed_time":0.4392954374,"remaining_time":0.6534792826},
{"learn":[4.154448767],"iteration":402,"passed_time":0.4401717933,"remaining_time":0.6520659071},
{"learn":[4.15197457],"iteration":403,"passed_time":0.4409718276,"remaining_time":0.6505425972},
{"learn":[4.149562679],"iteration":404,"passed_time":0.4416949639,"remaining_time":0.6489098852},
{"learn":[4.149327961],"iteration":405,"passed_time":0.4423912625,"remaining_time":0.647242389},
{"learn":[4.147444889],"iteration":406,"passed_time":0.4431437842,"remaining_time":0.6456615824},
{"learn":[4.147254809],"iteration":407,"passed_time":0.4438119383,"remaining_time":0.6439624202},
{"learn":[4.144589165],"iteration":408,"passed_time":0.444533987,"remaining_time":0.6423461768},
{"learn":[4.141691034],"iteration":409,"passed_time":0.445238807,"remaining_time":0.6407095027},
{"learn":[4.138893468],"iteration":410,"passed_time":0.4459513814,"remaining_time":0.639088476},
{"learn":[4.136964597],"iteration":411,"passed_time":0.4467145322,"remaining_time":0.6375440411},
{"learn":[4.133773523],"iteration":412,"passed_time":0.4474011787,"remaining_time":0.6358946536},
{"learn":[4.131363444],"iteration":413,"passed_time":0.4480304175,"remaining_time":0.6341686586},
{"learn":[4.130228592],"iteration":414,"passed_time":0.4490785925,"remaining_time":0.6330384978},
{"learn":[4.12884186],"iteration":415,"passed_time":0.4499264129,"remaining_time":0.6316274642},
{"learn":[4.12413494],"iteration":416,"passed_time":0.4507510358,"remaining_time":0.6301867},
{"learn":[4.119422508],"iteration":417,"passed_time":0.4515183042,"remaining_time":0.6286690264},
{"learn":[4.117038244],"iteration":418,"passed_time":0.4522400555,"remaining_time":0.6270918192},
{"learn":[4.116067631],"iteration":419,"passed_time":0.4528927413,"remaining_time":0.6254233094},
{"learn":[4.110343455],"iteration":420,"passed_time":0.453807028,"remaining_time":0.6241194042},
{"learn":[4.105604544],"iteration":421,"passed_time":0.4551198932,"remaining_time":0.623363266},
{"learn":[4.103390131],"iteration":422,"passed_time":0.4559809822,"remaining_time":0.6219882429},
{"learn":[4.096724402],"iteration":423,"passed_time":0.4566552084,"remaining_time":0.6203617925},
{"learn":[4.093431279],"iteration":424,"passed_time":0.4572760899,"remaining_time":0.618667651},
{"learn":[4.091412744],"iteration":425,"passed_time":0.4579025981,"remaining_time":0.6169861299},
{"learn":[4.091192901],"iteration":426,"passed_time":0.4585891861,"remaining_time":0.6153901724},
{"learn":[4.088994581],"iteration":427,"passed_time":0.459256995,"remaining_time":0.6137733671},
{"learn":[4.087845355],"iteration":428,"passed_time":0.4599405533,"remaining_time":0.6121819486},
{"learn":[4.083650279],"iteration":429,"passed_time":0.4605541161,"remaining_time":0.6105019679},
{"learn":[4.079840652],"iteration":430,"passed_time":0.4611897123,"remaining_time":0.6088560239},
{"learn":[4.075707828],"iteration":431,"passed_time":0.4618283527,"remaining_time":0.60721876},
{"learn":[4.071345409],"iteration":432,"passed_time":0.4625043638,"remaining_time":0.6056350445},
{"learn":[4.067460475],"iteration":433,"passed_time":0.4633813519,"remaining_time":0.6043176156},
{"learn":[4.064914749],"iteration":434,"passed_time":0.4641299558,"remaining_time":0.6028354599},
{"learn":[4.063823175],"iteration":435,"passed_time":0.4649811032,"remaining_time":0.601489317},
{"learn":[4.058898471],"iteration":436,"passed_time":0.4658300839,"remaining_time":0.6001426481},
{"learn":[4.054120355],"iteration":437,"passed_time":0.4666344709,"remaining_time":0.5987410334},
{"learn":[4.052715901],"iteration":438,"passed_time":0.4675291983,"remaining_time":0.597457586},
{"learn":[4.052114167],"iteration":439,"passed_time":0.4683933714,"remaining_time":0.5961370181},
{"learn":[4.051377267],"iteration":440,"passed_time":0.4692780101,"remaining_time":0.5948444617},
{"learn":[4.049275336],"iteration":441,"passed_time":0.4704605337,"remaining_time":0.5939298141},
{"learn":[4.047099198],"iteration":442,"passed_time":0.4714584319,"remaining_time":0.5927818207},
{"learn":[4.044348685],"iteration":443,"passed_time":0.4722099562,"remaining_time":0.5913259811},
{"learn":[4.042822379],"iteration":444,"passed_time":0.4730045798,"remaining_time":0.5899270602},
{"learn":[4.041258611],"iteration":445,"passed_time":0.4737993729,"remaining_time":0.5885310596},
{"learn":[4.040044254],"iteration":446,"passed_time":0.4746069619,"remaining_time":0.5871535793},
{"learn":[4.036860137],"iteration":447,"passed_time":0.4753833913,"remaining_time":0.58574025},
{"learn":[4.036372284],"iteration":448,"passed_time":0.4761458845,"remaining_time":0.5843126556},
{"learn":[4.03368231],"iteration":449,"passed_time":0.4770385374,"remaining_time":0.5830471012},
{"learn":[4.032439519],"iteration":450,"passed_time":0.4779573125,"remaining_time":0.581814999},
{"learn":[4.032008634],"iteration":451,"passed_time":0.4788320121,"remaining_time":0.5805308465},
{"learn":[4.030034932],"iteration":452,"passed_time":0.4796849794,"remaining_time":0.5792222599},
{"learn":[4.028173412],"iteration":453,"passed_time":0.4803752965,"remaining_time":0.5777200703},
{"learn":[4.023806097],"iteration":454,"passed_time":0.4812029487,"remaining_time":0.5763859495},
{"learn":[4.020239186],"iteration":455,"passed_time":0.4820320369,"remaining_time":0.5750557634},
{"learn":[4.017384838],"iteration":456,"passed_time":0.4829057998,"remaining_time":0.5737808518},
{"learn":[4.016468229],"iteration":457,"passed_time":0.4836974735,"remaining_time":0.5724105473},
{"learn":[4.014530169],"iteration":458,"passed_time":0.4847778338,"remaining_time":0.5713830241},
{"learn":[4.012884822],"iteration":459,"passed_time":0.4860257719,"remaining_time":0.5705519931},
{"learn":[4.008924707],"iteration":460,"passed_time":0.4869130522,"remaining_time":0.5692974732},
{"learn":[4.008286778],"iteration":461,"passed_time":0.4877562025,"remaining_time":0.5679931536},
{"learn":[4.006444202],"iteration":462,"passed_time":0.4885688205,"remaining_time":0.5666554139},
{"learn":[4.003284363],"iteration":463,"passed_time":0.4893351791,"remaining_time":0.5652665},
{"learn":[3.999811484],"iteration":464,"passed_time":0.4901233788,"remaining_time":0.5639053928},
{"learn":[3.997483319],"iteration":465,"passed_time":0.4909610004,"remaining_time":0.5626033782},
{"learn":[3.99708333],"iteration":466,"passed_time":0.4917354276,"remaining_time":0.5612312268},
{"learn":[3.995860263],"iteration":467,"passed_time":0.4924998877,"remaining_time":0.5598502997},
{"learn":[3.994131111],"iteration":468,"passed_time":0.4934123108,"remaining_time":0.5586395246},
{"learn":[3.993125499],"iteration":469,"passed_time":0.4943272933,"remaining_time":0.5574329052},
{"learn":[3.992954084],"iteration":470,"passed_time":0.4952343181,"remaining_time":0.5562185866},
{"learn":[3.990635743],"iteration":471,"passed_time":0.4963485714,"remaining_time":0.5552373849},
{"learn":[3.986678254],"iteration":472,"passed_time":0.4971942545,"remaining_time":0.5539563892},
{"learn":[3.986393291],"iteration":473,"passed_time":0.498047422,"remaining_time":0.5526855359},
{"learn":[3.986152671],"iteration":474,"passed_time":0.498989852,"remaining_time":0.5515150996},
{"learn":[3.985596662],"iteration":475,"passed_time":0.5011591001,"remaining_time":0.5516961522},
{"learn":[3.983853457],"iteration":476,"passed_time":0.5021409488,"remaining_time":0.5505654428},
{"learn":[3.983263928],"iteration":477,"passed_time":0.5029973703,"remaining_time":0.5492983834},
{"learn":[3.980067202],"iteration":478,"passed_time":0.5040229195,"remaining_time":0.5482169959},
{"learn":[3.978115407],"iteration":479,"passed_time":0.5049907024,"remaining_time":0.5470732609},
{"learn":[3.972661644],"iteration":480,"passed_time":0.5060156937,"remaining_time":0.5459919855},
{"learn":[3.969938254],"iteration":481,"passed_time":0.5069438318,"remaining_time":0.5448068566},
{"learn":[3.968211434],"iteration":482,"passed_time":0.507788041,"remaining_time":0.5435329549},
{"learn":[3.966113368],"iteration":483,"passed_time":0.508621862,"remaining_time":0.5422497538},
{"learn":[3.962246044],"iteration":484,"passed_time":0.5095189037,"remaining_time":0.5410355369},
{"learn":[3.961319703],"iteration":485,"passed_time":0.5103793995,"remaining_time":0.539783974},
{"learn":[3.96078191],"iteration":486,"passed_time":0.5112990641,"remaining_time":0.5385963447},
{"learn":[3.958913633],"iteration":487,"passed_time":0.5120965216,"remaining_time":0.5372815965},
{"learn":[3.957428286],"iteration":488,"passed_time":0.5130046236,"remaining_time":0.5360845863},
{"learn":[3.952641965],"iteration":489,"passed_time":0.5139769914,"remaining_time":0.5349556442},
{"learn":[3.951486786],"iteration":490,"passed_time":0.5151498846,"remaining_time":0.5340352164},
{"learn":[3.94938344],"iteration":491,"passed_time":0.5168001213,"remaining_time":0.5336066293},
{"learn":[3.947297924],"iteration":492,"passed_time":0.5178583115,"remaining_time":0.532564227},
{"learn":[3.946284886],"iteration":493,"passed_time":0.5187026831,"remaining_time":0.5313027483},
{"learn":[3.943288204],"iteration":494,"passed_time":0.5197616061,"remaining_time":0.5302618405},
{"learn":[3.943076488],"iteration":495,"passed_time":0.5206517249,"remaining_time":0.5290493334},
{"learn":[3.942347078],"iteration":496,"passed_time":0.5213898081,"remaining_time":0.5276842525},
{"learn":[3.940251541],"iteration":497,"passed_time":0.5223008018,"remaining_time":0.5264959889},
{"learn":[3.939011019],"iteration":498,"passed_time":0.523227537,"remaining_time":0.5253246414},
{"learn":[3.938760512],"iteration":499,"passed_time":0.5240693664,"remaining_time":0.5240693664},
{"learn":[3.934522727],"iteration":500,"passed_time":0.5249428891,"remaining_time":0.5228473087},
{"learn":[3.930091193],"iteration":501,"passed_time":0.5258067605,"remaining_time":0.5216170652},
{"learn":[3.927671752],"iteration":502,"passed_time":0.5267330601,"remaining_time":0.5204499619},
{"learn":[3.927280041],"iteration":503,"passed_time":0.5275679665,"remaining_time":0.5191938718},
{"learn":[3.925987561],"iteration":504,"passed_time":0.5284816458,"remaining_time":0.5180166628},
{"learn":[3.921645957],"iteration":505,"passed_time":0.5293450354,"remaining_time":0.5167913982},
{"learn":[3.920333743],"iteration":506,"passed_time":0.5312691592,"remaining_time":0.5165990049},
{"learn":[3.918659461],"iteration":507,"passed_time":0.5322975373,"remaining_time":0.5155322606},
{"learn":[3.916124385],"iteration":508,"passed_time":0.5332349013,"remaining_time":0.5143778714},
{"learn":[3.913849268],"iteration":509,"passed_time":0.5342232558,"remaining_time":0.5132733242},
{"learn":[3.912826119],"iteration":510,"passed_time":0.5353312634,"remaining_time":0.5122837334},
{"learn":[3.910034145],"iteration":511,"passed_time":0.5363232752,"remaining_time":0.5111831216},
{"learn":[3.90792379],"iteration":512,"passed_time":0.5373315948,"remaining_time":0.5100984145},
{"learn":[3.907823851],"iteration":513,"passed_time":0.5382894581,"remaining_time":0.5089662969},
{"learn":[3.904527401],"iteration":514,"passed_time":0.5392194385,"remaining_time":0.5078085974},
{"learn":[3.903378283],"iteration":515,"passed_time":0.5400710886,"remaining_time":0.5065783079},
{"learn":[3.902170135],"iteration":516,"passed_time":0.5410870854,"remaining_time":0.5055030218},
{"learn":[3.899435429],"iteration":517,"passed_time":0.5419130913,"remaining_time":0.5042511776},
{"learn":[3.897497505],"iteration":518,"passed_time":0.5428490732,"remaining_time":0.5031028983},
{"learn":[3.896426119],"iteration":519,"passed_time":0.5436905257,"remaining_time":0.5018681776},
{"learn":[3.896044669],"iteration":520,"passed_time":0.5447956998,"remaining_time":0.5008774284},
{"learn":[3.892795942],"iteration":521,"passed_time":0.5462536533,"remaining_time":0.5002092841},
{"learn":[3.892413888],"iteration":522,"passed_time":0.5475359613,"remaining_time":0.4993779226},
{"learn":[3.891738985],"iteration":523,"passed_time":0.5485114534,"remaining_time":0.4982661294},
{"learn":[3.88822057],"iteration":524,"passed_time":0.5494214144,"remaining_time":0.4970955654},
{"learn":[3.883837053],"iteration":525,"passed_time":0.550373486,"remaining_time":0.4959639398},
{"learn":[3.881769742],"iteration":526,"passed_time":0.5511563871,"remaining_time":0.4946811596},
{"learn":[3.880356898],"iteration":527,"passed_time":0.552071743,"remaining_time":0.4935186794},
{"learn":[3.879250273],"iteration":528,"passed_time":0.5529999015,"remaining_time":0.4923685323},
{"learn":[3.877174493],"iteration":529,"passed_time":0.5537718519,"remaining_time":0.4910806989},
{"learn":[3.875854201],"iteration":530,"passed_time":0.5550207517,"remaining_time":0.4902160688},
{"learn":[3.873189396],"iteration":531,"passed_time":0.5558844512,"remaining_time":0.4890111338},
{"learn":[3.871583368],"iteration":532,"passed_time":0.5568473472,"remaining_time":0.4878943924},
{"learn":[3.869622679],"iteration":533,"passed_time":0.5577168334,"remaining_time":0.4866967123},
{"learn":[3.866860164],"iteration":534,"passed_time":0.5587741312,"remaining_time":0.4856634972},
{"learn":[3.864498444],"iteration":535,"passed_time":0.5596174876,"remaining_time":0.4844449893},
{"learn":[3.861416322],"iteration":536,"passed_time":0.5608612433,"remaining_time":0.4835731018},
{"learn":[3.860265769],"iteration":537,"passed_time":0.562217247,"remaining_time":0.4827962232},
{"learn":[3.859328725],"iteration":538,"passed_time":0.5633358662,"remaining_time":0.4818141639},
{"learn":[3.858521278],"iteration":539,"passed_time":0.5644252675,"remaining_time":0.4808067093},
{"learn":[3.85599111],"iteration":540,"passed_time":0.5655457868,"remaining_time":0.4798253533},
{"learn":[3.852379816],"iteration":541,"passed_time":0.5664713536,"remaining_time":0.4786787453},
{"learn":[3.851327537],"iteration":542,"passed_time":0.5674062438,"remaining_time":0.4775407982},
{"learn":[3.847854898],"iteration":543,"passed_time":0.568210637,"remaining_time":0.4762942105},
{"learn":[3.847083414],"iteration":544,"passed_time":0.5695783482,"remaining_time":0.4755195384},
{"learn":[3.845397429],"iteration":545,"passed_time":0.5705922156,"remaining_time":0.4744484723},
{"learn":[3.841933528],"iteration":546,"passed_time":0.5716037547,"remaining_time":0.4733756871},
{"learn":[3.840996474],"iteration":547,"passed_time":0.5724626242,"remaining_time":0.472177201},
{"learn":[3.838355966],"iteration":548,"passed_time":0.5733149916,"remaining_time":0.4709746106},
{"learn":[3.83342799],"iteration":549,"passed_time":0.574175593,"remaining_time":0.4697800306},
{"learn":[3.828161535],"iteration":550,"passed_time":0.5750404228,"remaining_time":0.4685901086},
{"learn":[3.823502399],"iteration":551,"passed_time":0.576146571,"remaining_time":0.467597217},
{"learn":[3.820068862],"iteration":552,"passed_time":0.5775403862,"remaining_time":0.4668364424},
{"learn":[3.817951642],"iteration":553,"passed_time":0.5786329027,"remaining_time":0.4658308206},
{"learn":[3.815785958],"iteration":554,"passed_time":0.5796282706,"remaining_time":0.4647469917},
{"learn":[3.81503012],"iteration":555,"passed_time":0.5805354375,"remaining_time":0.4635930472},
{"learn":[3.813529315],"iteration":556,"passed_time":0.5814533386,"remaining_time":0.462448526},
{"learn":[3.808881326],"iteration":557,"passed_time":0.5823760502,"remaining_time":0.4613086276},
{"learn":[3.808740434],"iteration":558,"passed_time":0.5831371264,"remaining_time":0.4600419906},
{"learn":[3.80714352],"iteration":559,"passed_time":0.5840507941,"remaining_time":0.4588970525},
{"learn":[3.80573346],"iteration":560,"passed_time":0.5849286599,"remaining_time":0.4577249228},
{"learn":[3.803370052],"iteration":561,"passed_time":0.5856594278,"remaining_time":0.4564391981},
{"learn":[3.803215211],"iteration":562,"passed_time":0.5864862973,"remaining_time":0.4552300389},
{"learn":[3.801309667],"iteration":563,"passed_time":0.5873182082,"remaining_time":0.4540261326},
{"learn":[3.800003847],"iteration":564,"passed_time":0.5881554094,"remaining_time":0.4528276161},
{"learn":[3.798026138],"iteration":565,"passed_time":0.5890093202,"remaining_time":0.451643189},
{"learn":[3.794745847],"iteration":566,"passed_time":0.590021408,"remaining_time":0.4505807225},
{"learn":[3.794312041],"iteration":567,"passed_time":0.5920776321,"remaining_time":0.4503125653},
{"learn":[3.792205926],"iteration":568,"passed_time":0.5934276381,"remaining_time":0.4495031846},
{"learn":[3.788991061],"iteration":569,"passed_time":0.5945670561,"remaining_time":0.4485330424},
{"learn":[3.787391572],"iteration":570,"passed_time":0.5953893237,"remaining_time":0.4473240278},
{"learn":[3.7826445],"iteration":571,"passed_time":0.5963694896,"remaining_time":0.4462345132},
{"learn":[3.781700331],"iteration":572,"passed_time":0.5971841565,"remaining_time":0.4450220503},
{"learn":[3.780045374],"iteration":573,"passed_time":0.5980467555,"remaining_time":0.4438465468},
{"learn":[3.775462644],"iteration":574,"passed_time":0.5989534085,"remaining_time":0.4427046933},
{"learn":[3.773711943],"iteration":575,"passed_time":0.5997995635,"remaining_time":0.4415191232},
{"learn":[3.772415806],"iteration":576,"passed_time":0.6007476476,"remaining_time":0.440409454},
{"learn":[3.770170875],"iteration":577,"passed_time":0.6017381141,"remaining_time":0.4393312875},
{"learn":[3.765166479],"iteration":578,"passed_time":0.6026200277,"remaining_time":0.4381744934},
{"learn":[3.763976102],"iteration":579,"passed_time":0.6036621199,"remaining_time":0.4371346385},
{"learn":[3.760761708],"iteration":580,"passed_time":0.6047218292,"remaining_time":0.4361074809},
{"learn":[3.758155662],"iteration":581,"passed_time":0.6061716556,"remaining_time":0.4353603987},
{"learn":[3.756844548],"iteration":582,"passed_time":0.6074931685,"remaining_time":0.4345191274},
{"learn":[3.753098923],"iteration":583,"passed_time":0.6086908285,"remaining_time":0.4335879874},
{"learn":[3.751618946],"iteration":584,"passed_time":0.6096821241,"remaining_time":0.432509541},
{"learn":[3.751398464],"iteration":585,"passed_time":0.6106865043,"remaining_time":0.4314406362},
{"learn":[3.749920103],"iteration":586,"passed_time":0.6116440669,"remaining_time":0.4303390113},
{"learn":[3.748237465],"iteration":587,"passed_time":0.6125283936,"remaining_time":0.4291865615},
{"learn":[3.746021536],"iteration":588,"passed_time":0.6134453003,"remaining_time":0.4280577562},
{"learn":[3.74417648],"iteration":589,"passed_time":0.6144140166,"remaining_time":0.4269656725},
{"learn":[3.738788389],"iteration":590,"passed_time":0.6153126796,"remaining_time":0.4258255262},
{"learn":[3.736021611],"iteration":591,"passed_time":0.6161863992,"remaining_time":0.4246690049},
{"learn":[3.734546151],"iteration":592,"passed_time":0.6170841733,"remaining_time":0.4235299469},
{"learn":[3.733527479],"iteration":593,"passed_time":0.618055633,"remaining_time":0.4224420656},
{"learn":[3.733026392],"iteration":594,"passed_time":0.619005773,"remaining_time":0.4213400639},
{"learn":[3.730314752],"iteration":595,"passed_time":0.6197841727,"remaining_time":0.4201221573},
{"learn":[3.727342596],"iteration":596,"passed_time":0.6207601313,"remaining_time":0.4190390836},
{"learn":[3.725459604],"iteration":597,"passed_time":0.6223658986,"remaining_time":0.4183797512},
{"learn":[3.723158842],"iteration":598,"passed_time":0.6232442854,"remaining_time":0.4172303146},
{"learn":[3.722362756],"iteration":599,"passed_time":0.6240238208,"remaining_time":0.4160158806},
{"learn":[3.721443615],"iteration":600,"passed_time":0.6247919221,"remaining_time":0.4147953027},
{"learn":[3.720743486],"iteration":601,"passed_time":0.6255852687,"remaining_time":0.4135929185},
{"learn":[3.720215334],"iteration":602,"passed_time":0.6262591418,"remaining_time":0.4123132327},
{"learn":[3.719436563],"iteration":603,"passed_time":0.627006809,"remaining_time":0.4110839343},
{"learn":[3.715046574],"iteration":604,"passed_time":0.6277606167,"remaining_time":0.4098602374},
{"learn":[3.71443396],"iteration":605,"passed_time":0.628507986,"remaining_time":0.4086339051},
{"learn":[3.712938941],"iteration":606,"passed_time":0.6292853161,"remaining_time":0.407428549},
{"learn":[3.712814764],"iteration":607,"passed_time":0.6300505485,"remaining_time":0.406216801},
{"learn":[3.71235348],"iteration":608,"passed_time":0.6307982393,"remaining_time":0.4049952571},
{"learn":[3.711223749],"iteration":609,"passed_time":0.6315291775,"remaining_time":0.4037645561},
{"learn":[3.710755648],"iteration":610,"passed_time":0.6322900302,"remaining_time":0.4025545364},
{"learn":[3.708668039],"iteration":611,"passed_time":0.6331145257,"remaining_time":0.4013863333},
{"learn":[3.705623591],"iteration":612,"passed_time":0.6339223515,"remaining_time":0.4002087276},
{"learn":[3.704045802],"iteration":613,"passed_time":0.6347544842,"remaining_time":0.3990476074},
{"learn":[3.699915209],"iteration":614,"passed_time":0.6356353838,"remaining_time":0.3979180858},
{"learn":[3.696182221],"iteration":615,"passed_time":0.6365157621,"remaining_time":0.3967890465},
{"learn":[3.694263278],"iteration":616,"passed_time":0.6375690438,"remaining_time":0.3957681422},
{"learn":[3.693810229],"iteration":617,"passed_time":0.6383835286,"remaining_time":0.3945995274},
{"learn":[3.690900932],"iteration":618,"passed_time":0.6393217238,"remaining_time":0.3935082016},
{"learn":[3.688020895],"iteration":619,"passed_time":0.6402108395,"remaining_time":0.3923872887},
{"learn":[3.685491894],"iteration":620,"passed_time":0.6410146125,"remaining_time":0.3912150373},
{"learn":[3.684328128],"iteration":621,"passed_time":0.6418022826,"remaining_time":0.3900341846},
{"learn":[3.680640153],"iteration":622,"passed_time":0.6425869874,"remaining_time":0.3888527998},
{"learn":[3.678932783],"iteration":623,"passed_time":0.643412356,"remaining_time":0.3876971889},
{"learn":[3.674167041],"iteration":624,"passed_time":0.6441652258,"remaining_time":0.3864991355},
{"learn":[3.672200976],"iteration":625,"passed_time":0.6449871125,"remaining_time":0.3853437381},
{"learn":[3.670606604],"iteration":626,"passed_time":0.6457418707,"remaining_time":0.3841494701},
{"learn":[3.665506042],"iteration":627,"passed_time":0.6465296413,"remaining_time":0.3829761569},
{"learn":[3.664214007],"iteration":628,"passed_time":0.6473722449,"remaining_time":0.3818364115},
{"learn":[3.66261643],"iteration":629,"passed_time":0.6481168451,"remaining_time":0.3806400519},
{"learn":[3.662118449],"iteration":630,"passed_time":0.6487214254,"remaining_time":0.3793632424},
{"learn":[3.660871366],"iteration":631,"passed_time":0.649393727,"remaining_time":0.3781279929},
{"learn":[3.656695243],"iteration":632,"passed_time":0.6500431788,"remaining_time":0.3768812743},
{"learn":[3.654497801],"iteration":633,"passed_time":0.6507763249,"remaining_time":0.3756847554},
{"learn":[3.654189134],"iteration":634,"passed_time":0.6514581152,"remaining_time":0.3744601765},
{"learn":[3.653957699],"iteration":635,"passed_time":0.6525615566,"remaining_time":0.3734786267},
{"learn":[3.651920725],"iteration":636,"passed_time":0.6532446555,"remaining_time":0.3722571585},
{"learn":[3.65106705],"iteration":637,"passed_time":0.653860781,"remaining_time":0.3709993773},
{"learn":[3.650612844],"iteration":638,"passed_time":0.6545472368,"remaining_time":0.3697833372},
{"learn":[3.649884732],"iteration":639,"passed_time":0.655254089,"remaining_time":0.368580425},
{"learn":[3.646276182],"iteration":640,"passed_time":0.6559204676,"remaining_time":0.3673563929},
{"learn":[3.645808194],"iteration":641,"passed_time":0.6565601685,"remaining_time":0.3661192217},
{"learn":[3.645042989],"iteration":642,"passed_time":0.6571759795,"remaining_time":0.3648706449},
{"learn":[3.639864499],"iteration":643,"passed_time":0.6578250774,"remaining_time":0.3636424341},
{"learn":[3.637318478],"iteration":644,"passed_time":0.6584434456,"remaining_time":0.3623991057},
{"learn":[3.636344905],"iteration":645,"passed_time":0.6590527484,"remaining_time":0.3611527445},
{"learn":[3.634754643],"iteration":646,"passed_time":0.6596782795,"remaining_time":0.3599172066},
{"learn":[3.630724975],"iteration":647,"passed_time":0.6602881929,"remaining_time":0.3586750678},
{"learn":[3.629408252],"iteration":648,"passed_time":0.6608966777,"remaining_time":0.3574341046},
{"learn":[3.62790646],"iteration":649,"passed_time":0.6614996674,"remaining_time":0.3561921286},
{"learn":[3.627388973],"iteration":650,"passed_time":0.6620830419,"remaining_time":0.3549416},
{"learn":[3.625163557],"iteration":651,"passed_time":0.6627257233,"remaining_time":0.3537247726},
{"learn":[3.623701985],"iteration":652,"passed_time":0.6633452572,"remaining_time":0.3524974031},
{"learn":[3.622342639],"iteration":653,"passed_time":0.6639465188,"remaining_time":0.3512622256},
{"learn":[3.621130639],"iteration":654,"passed_time":0.6645543074,"remaining_time":0.3500324215},
{"learn":[3.619125665],"iteration":655,"passed_time":0.6652020706,"remaining_time":0.348825476},
{"learn":[3.618878783],"iteration":656,"passed_time":0.665844983,"remaining_time":0.3476177004},
{"learn":[3.616207429],"iteration":657,"passed_time":0.6665843125,"remaining_time":0.3464617551},
{"learn":[3.61206486],"iteration":658,"passed_time":0.6678048442,"remaining_time":0.3455560726},
{"learn":[3.611955873],"iteration":659,"passed_time":0.6685208587,"remaining_time":0.3443895332},
{"learn":[3.610713743],"iteration":660,"passed_time":0.6691476539,"remaining_time":0.3431786001},
{"learn":[3.610044025],"iteration":661,"passed_time":0.6697525982,"remaining_time":0.3419582752},
{"learn":[3.607342669],"iteration":662,"passed_time":0.6703469349,"remaining_time":0.3407344149},
{"learn":[3.602510618],"iteration":663,"passed_time":0.6710143055,"remaining_time":0.3395494076},
{"learn":[3.600492392],"iteration":664,"passed_time":0.6716341647,"remaining_time":0.3383420228},
{"learn":[3.597171065],"iteration":665,"passed_time":0.6722362554,"remaining_time":0.3371274915},
{"learn":[3.594358798],"iteration":666,"passed_time":0.672851187,"remaining_time":0.3359212073},
{"learn":[3.593945251],"iteration":667,"passed_time":0.6734272398,"remaining_time":0.3346973707},
{"learn":[3.593607748],"iteration":668,"passed_time":0.6740314359,"remaining_time":0.333489395},
{"learn":[3.592238714],"iteration":669,"passed_time":0.6746412101,"remaining_time":0.3322859691},
{"learn":[3.590144654],"iteration":670,"passed_time":0.6752335316,"remaining_time":0.3310757554},
{"learn":[3.587151536],"iteration":671,"passed_time":0.675883128,"remaining_time":0.3298953363},
{"learn":[3.586070865],"iteration":672,"passed_time":0.6766078566,"remaining_time":0.3287530002},
{"learn":[3.585102746],"iteration":673,"passed_time":0.6772494202,"remaining_time":0.327571678},
{"learn":[3.584362847],"iteration":674,"passed_time":0.6778469888,"remaining_time":0.3263707724},
{"learn":[3.581407561],"iteration":675,"passed_time":0.6785308396,"remaining_time":0.325213006},
{"learn":[3.57919422],"iteration":676,"passed_time":0.6791610753,"remaining_time":0.3240310596},
{"learn":[3.577632204],"iteration":677,"passed_time":0.6797977445,"remaining_time":0.3228537961},
{"learn":[3.573911195],"iteration":678,"passed_time":0.6803961444,"remaining_time":0.3216600329},
{"learn":[3.573408216],"iteration":679,"passed_time":0.6810162333,"remaining_time":0.3204782274},
{"learn":[3.571076482],"iteration":680,"passed_time":0.681801626,"remaining_time":0.3193755047},
{"learn":[3.568177107],"iteration":681,"passed_time":0.6830094777,"remaining_time":0.3184706949},
{"learn":[3.564824621],"iteration":682,"passed_time":0.6836765542,"remaining_time":0.3173140083},
{"learn":[3.562475026],"iteration":683,"passed_time":0.684466846,"remaining_time":0.3162156774},
{"learn":[3.561226889],"iteration":684,"passed_time":0.6851295635,"remaining_time":0.3150595803},
{"learn":[3.559383467],"iteration":685,"passed_time":0.6857802059,"remaining_time":0.3138993946},
{"learn":[3.555209766],"iteration":686,"passed_time":0.6864684377,"remaining_time":0.312757818},
{"learn":[3.55345383],"iteration":687,"passed_time":0.6871155221,"remaining_time":0.3115988996},
{"learn":[3.552300968],"iteration":688,"passed_time":0.6877569175,"remaining_time":0.3104388989},
{"learn":[3.551253986],"iteration":689,"passed_time":0.6884437833,"remaining_time":0.3093008302},
{"learn":[3.549807725],"iteration":690,"passed_time":0.6890468408,"remaining_time":0.3081265902},
{"learn":[3.547992926],"iteration":691,"passed_time":0.6896778031,"remaining_time":0.306966421},
{"learn":[3.545438607],"iteration":692,"passed_time":0.6903786729,"remaining_time":0.3058387483},
{"learn":[3.543313763],"iteration":693,"passed_time":0.6909771683,"remaining_time":0.3046671664},
{"learn":[3.542962896],"iteration":694,"passed_time":0.6916120882,"remaining_time":0.3035132185},
{"learn":[3.539800465],"iteration":695,"passed_time":0.692207964,"remaining_time":0.3023437084},
{"learn":[3.53953187],"iteration":696,"passed_time":0.6928166818,"remaining_time":0.301181427},
{"learn":[3.536332425],"iteration":697,"passed_time":0.6934720852,"remaining_time":0.3000409309},
{"learn":[3.534993327],"iteration":698,"passed_time":0.6941698042,"remaining_time":0.2989200444},
{"learn":[3.531637011],"iteration":699,"passed_time":0.6948647444,"remaining_time":0.2977991762},
{"learn":[3.531040284],"iteration":700,"passed_time":0.6954803298,"remaining_time":0.2966456756},
{"learn":[3.529973872],"iteration":701,"passed_time":0.6963336482,"remaining_time":0.2955946256},
{"learn":[3.527325183],"iteration":702,"passed_time":0.6974122716,"remaining_time":0.2946393238},
{"learn":[3.527200815],"iteration":703,"passed_time":0.698485596,"remaining_time":0.2936814438},
{"learn":[3.523459911],"iteration":704,"passed_time":0.6992346099,"remaining_time":0.2925875318},
{"learn":[3.522729934],"iteration":705,"passed_time":0.6999561481,"remaining_time":0.2914831552},
{"learn":[3.522260582],"iteration":706,"passed_time":0.7005947881,"remaining_time":0.2903455062},
{"learn":[3.518641591],"iteration":707,"passed_time":0.7013529581,"remaining_time":0.2892585646},
{"learn":[3.516856405],"iteration":708,"passed_time":0.702236024,"remaining_time":0.2882238124},
{"learn":[3.515083413],"iteration":709,"passed_time":0.7029651572,"remaining_time":0.2871266135},
{"learn":[3.514671214],"iteration":710,"passed_time":0.7035775331,"remaining_time":0.2859829917},
{"learn":[3.512617621],"iteration":711,"passed_time":0.7042022626,"remaining_time":0.284845859},
{"learn":[3.510747971],"iteration":712,"passed_time":0.7047845773,"remaining_time":0.2836930907},
{"learn":[3.508149266],"iteration":713,"passed_time":0.7053723796,"remaining_time":0.2825441184},
{"learn":[3.504557165],"iteration":714,"passed_time":0.7059661102,"remaining_time":0.2813990789},
{"learn":[3.501367208],"iteration":715,"passed_time":0.7065642828,"remaining_time":0.2802573412},
{"learn":[3.497593362],"iteration":716,"passed_time":0.7071899764,"remaining_time":0.2791279823},
{"learn":[3.496291169],"iteration":717,"passed_time":0.7077966151,"remaining_time":0.2779925424},
{"learn":[3.49330374],"iteration":718,"passed_time":0.7083902868,"remaining_time":0.2768535057},
{"learn":[3.490044385],"iteration":719,"passed_time":0.7090836301,"remaining_time":0.2757547451},
{"learn":[3.488891789],"iteration":720,"passed_time":0.7097641319,"remaining_time":0.2746521398},
{"learn":[3.486869081],"iteration":721,"passed_time":0.71037885,"remaining_time":0.2735253744},
{"learn":[3.486303638],"iteration":722,"passed_time":0.7110142522,"remaining_time":0.27240795},
{"learn":[3.486035862],"iteration":723,"passed_time":0.7116512284,"remaining_time":0.2712924572},
{"learn":[3.482668951],"iteration":724,"passed_time":0.7125772491,"remaining_time":0.2702879221},
{"learn":[3.47820549],"iteration":725,"passed_time":0.713655296,"remaining_time":0.2693409795},
{"learn":[3.474392283],"iteration":726,"passed_time":0.714278635,"remaining_time":0.2682229262},
{"learn":[3.472268163],"iteration":727,"passed_time":0.7148936779,"remaining_time":0.2671031324},
{"learn":[3.471209164],"iteration":728,"passed_time":0.7154917467,"remaining_time":0.2659784134},
{"learn":[3.470049971],"iteration":729,"passed_time":0.7160893685,"remaining_time":0.2648549719},
{"learn":[3.469078654],"iteration":730,"passed_time":0.7167079918,"remaining_time":0.2637406974},
{"learn":[3.468643292],"iteration":731,"passed_time":0.7173150559,"remaining_time":0.262623545},
{"learn":[3.468134848],"iteration":732,"passed_time":0.7179022824,"remaining_time":0.2615005585},
{"learn":[3.467820182],"iteration":733,"passed_time":0.7185025566,"remaining_time":0.2603837603},
{"learn":[3.465776156],"iteration":734,"passed_time":0.7191128509,"remaining_time":0.2592719802},
{"learn":[3.463037608],"iteration":735,"passed_time":0.7197303808,"remaining_time":0.2581641583},
{"learn":[3.45965637],"iteration":736,"passed_time":0.7203283952,"remaining_time":0.2570507028},
{"learn":[3.457275091],"iteration":737,"passed_time":0.7209480645,"remaining_time":0.2559463318},
{"learn":[3.455522955],"iteration":738,"passed_time":0.7215606286,"remaining_time":0.2548407633},
{"learn":[3.451270508],"iteration":739,"passed_time":0.7221585819,"remaining_time":0.2537313936},
{"learn":[3.450978947],"iteration":740,"passed_time":0.7227482195,"remaining_time":0.2526204978},
{"learn":[3.450608492],"iteration":741,"passed_time":0.723381017,"remaining_time":0.251526014},
{"learn":[3.448122004],"iteration":742,"passed_time":0.724216464,"remaining_time":0.2505028684},
{"learn":[3.445646714],"iteration":743,"passed_time":0.7249869227,"remaining_time":0.2494578659},
{"learn":[3.44411263],"iteration":744,"passed_time":0.7257626127,"remaining_time":0.2484153909},
{"learn":[3.443264164],"iteration":745,"passed_time":0.7265574752,"remaining_time":0.2473801591},
{"learn":[3.439521363],"iteration":746,"passed_time":0.7274775468,"remaining_time":0.2463879777},
{"learn":[3.436809225],"iteration":747,"passed_time":0.7287388317,"remaining_time":0.2455109433},
{"learn":[3.435509465],"iteration":748,"passed_time":0.7295783168,"remaining_time":0.2444915321},
{"learn":[3.434450277],"iteration":749,"passed_time":0.7302604902,"remaining_time":0.2434201634},
{"learn":[3.431786753],"iteration":750,"passed_time":0.7310745052,"remaining_time":0.2423935443},
{"learn":[3.430150302],"iteration":751,"passed_time":0.7318013561,"remaining_time":0.2413387451},
{"learn":[3.42696281],"iteration":752,"passed_time":0.7326488001,"remaining_time":0.240324374},
{"learn":[3.426870334],"iteration":753,"passed_time":0.7333670869,"remaining_time":0.2392683069},
{"learn":[3.425200309],"iteration":754,"passed_time":0.7340874312,"remaining_time":0.2382138022},
{"learn":[3.423383783],"iteration":755,"passed_time":0.7349377333,"remaining_time":0.2372021256},
{"learn":[3.422752979],"iteration":756,"passed_time":0.735632514,"remaining_time":0.2361409523},
{"learn":[3.420845924],"iteration":757,"passed_time":0.7363380065,"remaining_time":0.2350841657},
{"learn":[3.418917862],"iteration":758,"passed_time":0.7371975012,"remaining_time":0.2340772039},
{"learn":[3.417095735],"iteration":759,"passed_time":0.7379252539,"remaining_time":0.2330290276},
{"learn":[3.414391848],"iteration":760,"passed_time":0.73879518,"remaining_time":0.2320263443},
{"learn":[3.41426711],"iteration":761,"passed_time":0.7396056046,"remaining_time":0.2310054251},
{"learn":[3.411976013],"iteration":762,"passed_time":0.7403892286,"remaining_time":0.2299767329},
{"learn":[3.408614844],"iteration":763,"passed_time":0.7411882028,"remaining_time":0.2289534239},
{"learn":[3.407906721],"iteration":764,"passed_time":0.741938173,"remaining_time":0.2279156479},
{"learn":[3.407494015],"iteration":765,"passed_time":0.7427579627,"remaining_time":0.226899952},
{"learn":[3.406287128],"iteration":766,"passed_time":0.7441521169,"remaining_time":0.226059248},
{"learn":[3.404600442],"iteration":767,"passed_time":0.7450132624,"remaining_time":0.2250560897},
{"learn":[3.404012662],"iteration":768,"passed_time":0.7457906527,"remaining_time":0.2240281414},
{"learn":[3.400398762],"iteration":769,"passed_time":0.746491434,"remaining_time":0.2229779608},
{"learn":[3.399737714],"iteration":770,"passed_time":0.74725602,"remaining_time":0.2219476376},
{"learn":[3.399185251],"iteration":771,"passed_time":0.74810674,"remaining_time":0.2209434413},
{"learn":[3.397245411],"iteration":772,"passed_time":0.7489186609,"remaining_time":0.2199282484},
{"learn":[3.396229831],"iteration":773,"passed_time":0.7496730046,"remaining_time":0.2188967688},
{"learn":[3.394002836],"iteration":774,"passed_time":0.7503196699,"remaining_time":0.2178347429},
{"learn":[3.389617243],"iteration":775,"passed_time":0.7510400507,"remaining_time":0.2167950662},
{"learn":[3.385426488],"iteration":776,"passed_time":0.751757296,"remaining_time":0.2157553115},
{"learn":[3.385072258],"iteration":777,"passed_time":0.7533026671,"remaining_time":0.2149526891},
{"learn":[3.383842366],"iteration":778,"passed_time":0.7540874621,"remaining_time":0.2139323865},
{"learn":[3.380110746],"iteration":779,"passed_time":0.7548863736,"remaining_time":0.2129166695},
{"learn":[3.378595218],"iteration":780,"passed_time":0.7557499817,"remaining_time":0.2119196491},
{"learn":[3.377371219],"iteration":781,"passed_time":0.7565158243,"remaining_time":0.2108957157},
{"learn":[3.375814782],"iteration":782,"passed_time":0.7573321445,"remaining_time":0.2098864308},
{"learn":[3.374195887],"iteration":783,"passed_time":0.7582714584,"remaining_time":0.2089115243},
{"learn":[3.373704309],"iteration":784,"passed_time":0.7594141391,"remaining_time":0.2079924075},
{"learn":[3.372971757],"iteration":785,"passed_time":0.7601470928,"remaining_time":0.2069611678},
{"learn":[3.371565136],"iteration":786,"passed_time":0.7608711713,"remaining_time":0.205928284},
{"learn":[3.3700309],"iteration":787,"passed_time":0.7615913955,"remaining_time":0.204895147},
{"learn":[3.368186663],"iteration":788,"passed_time":0.7624186281,"remaining_time":0.2038914202},
{"learn":[3.366710398],"iteration":789,"passed_time":0.7631639569,"remaining_time":0.2028663683},
{"learn":[3.364598042],"iteration":790,"passed_time":0.7638983222,"remaining_time":0.2018391268},
{"learn":[3.36348442],"iteration":791,"passed_time":0.7646390262,"remaining_time":0.2008142897},
{"learn":[3.362001759],"iteration":792,"passed_time":0.7654117356,"remaining_time":0.1997985237},
{"learn":[3.361580401],"iteration":793,"passed_time":0.7661927765,"remaining_time":0.1987855314},
{"learn":[3.359543675],"iteration":794,"passed_time":0.766927315,"remaining_time":0.1977611315},
{"learn":[3.35766119],"iteration":795,"passed_time":0.7676687984,"remaining_time":0.1967392398},
{"learn":[3.354592969],"iteration":796,"passed_time":0.7683922142,"remaining_time":0.1957134498},
{"learn":[3.350985986],"iteration":797,"passed_time":0.7690877605,"remaining_time":0.1946813629},
{"learn":[3.349589624],"iteration":798,"passed_time":0.7697647209,"remaining_time":0.1936454429},
{"learn":[3.349110856],"iteration":799,"passed_time":0.7704721796,"remaining_time":0.1926180449},
{"learn":[3.345315441],"iteration":800,"passed_time":0.7712648387,"remaining_time":0.1916126129},
{"learn":[3.34397474],"iteration":801,"passed_time":0.7719995671,"remaining_time":0.1905934093},
{"learn":[3.343800902],"iteration":802,"passed_time":0.772728883,"remaining_time":0.1895735865},
{"learn":[3.342329465],"iteration":803,"passed_time":0.7736105603,"remaining_time":0.1885916291},
{"learn":[3.34220347],"iteration":804,"passed_time":0.7747274078,"remaining_time":0.1876668876},
{"learn":[3.341279219],"iteration":805,"passed_time":0.7755435048,"remaining_time":0.1866692803},
{"learn":[3.337329521],"iteration":806,"passed_time":0.7763389223,"remaining_time":0.1856671772},
{"learn":[3.336708453],"iteration":807,"passed_time":0.7770459847,"remaining_time":0.1846445904},
{"learn":[3.333252703],"iteration":808,"passed_time":0.777784418,"remaining_time":0.1836301902},
{"learn":[3.332186769],"iteration":809,"passed_time":0.7784942919,"remaining_time":0.1826097722},
{"learn":[3.330594851],"iteration":810,"passed_time":0.7791779616,"remaining_time":0.1815840132},
{"learn":[3.327867442],"iteration":811,"passed_time":0.7800249819,"remaining_time":0.180596917},
{"learn":[3.327563111],"iteration":812,"passed_time":0.7809551705,"remaining_time":0.1796292951},
{"learn":[3.326308994],"iteration":813,"passed_time":0.7816731021,"remaining_time":0.1786132641},
{"learn":[3.326249879],"iteration":814,"passed_time":0.7823845383,"remaining_time":0.1775964903},
{"learn":[3.322336238],"iteration":815,"passed_time":0.783087805,"remaining_time":0.1765786227},
{"learn":[3.320491154],"iteration":816,"passed_time":0.7838630065,"remaining_time":0.1755776379},
{"learn":[3.320434271],"iteration":817,"passed_time":0.7846035153,"remaining_time":0.1745694863},
{"learn":[3.319609638],"iteration":818,"passed_time":0.7853159385,"remaining_time":0.1735557813},
{"learn":[3.316182682],"iteration":819,"passed_time":0.7860220612,"remaining_time":0.1725414281},
{"learn":[3.313126612],"iteration":820,"passed_time":0.787001874,"remaining_time":0.1715874975},
{"learn":[3.311222803],"iteration":821,"passed_time":0.7877346661,"remaining_time":0.1705800129},
{"learn":[3.309627335],"iteration":822,"passed_time":0.7887365581,"remaining_time":0.1696310702},
{"learn":[3.307974895],"iteration":823,"passed_time":0.789940141,"remaining_time":0.1687250787},
{"learn":[3.307321505],"iteration":824,"passed_time":0.7907268839,"remaining_time":0.1677299451},
{"learn":[3.306759087],"iteration":825,"passed_time":0.7915554956,"remaining_time":0.1667441359},
{"learn":[3.30484037],"iteration":826,"passed_time":0.792327817,"remaining_time":0.1657469315},
{"learn":[3.30201994],"iteration":827,"passed_time":0.7930393355,"remaining_time":0.1647376397},
{"learn":[3.299302297],"iteration":828,"passed_time":0.7937714513,"remaining_time":0.1637333151},
{"learn":[3.298132671],"iteration":829,"passed_time":0.7944957981,"remaining_time":0.162728055},
{"learn":[3.296976183],"iteration":830,"passed_time":0.7952938044,"remaining_time":0.1617384512},
{"learn":[3.293144745],"iteration":831,"passed_time":0.7959813021,"remaining_time":0.1607269937},
{"learn":[3.290284404],"iteration":832,"passed_time":0.7967622895,"remaining_time":0.1597350568},
{"learn":[3.288285745],"iteration":833,"passed_time":0.7975243353,"remaining_time":0.1587398557},
{"learn":[3.286662667],"iteration":834,"passed_time":0.7982527543,"remaining_time":0.1577385682},
{"learn":[3.285692682],"iteration":835,"passed_time":0.7990136615,"remaining_time":0.1567443068},
{"learn":[3.284565611],"iteration":836,"passed_time":0.7997786825,"remaining_time":0.1557514041},
{"learn":[3.283897383],"iteration":837,"passed_time":0.8005454627,"remaining_time":0.1547593854},
{"learn":[3.280712855],"iteration":838,"passed_time":0.8013485088,"remaining_time":0.1537748628},
{"learn":[3.280468341],"iteration":839,"passed_time":0.8021211048,"remaining_time":0.1527849723},
{"learn":[3.277814895],"iteration":840,"passed_time":0.8028172069,"remaining_time":0.1517811366},
{"learn":[3.276316385],"iteration":841,"passed_time":0.8035446598,"remaining_time":0.1507839148},
{"learn":[3.27557063],"iteration":842,"passed_time":0.804802888,"remaining_time":0.1498861844},
{"learn":[3.27499628],"iteration":843,"passed_time":0.8056718354,"remaining_time":0.1489156473},
{"learn":[3.273569958],"iteration":844,"passed_time":0.8064997235,"remaining_time":0.1479378191},
{"learn":[3.269665595],"iteration":845,"passed_time":0.8072376472,"remaining_time":0.1469439689},
{"learn":[3.267984685],"iteration":846,"passed_time":0.8081211265,"remaining_time":0.1459770158},
{"learn":[3.267702508],"iteration":847,"passed_time":0.8091425033,"remaining_time":0.145034977},
{"learn":[3.266671924],"iteration":848,"passed_time":0.809999334,"remaining_time":0.1440634858},
{"learn":[3.265359825],"iteration":849,"passed_time":0.8108304,"remaining_time":0.1430877176},
{"learn":[3.2618983],"iteration":850,"passed_time":0.8116370514,"remaining_time":0.1421080149},
{"learn":[3.260456253],"iteration":851,"passed_time":0.8125017932,"remaining_time":0.1411388091},
{"learn":[3.258389147],"iteration":852,"passed_time":0.8133364413,"remaining_time":0.1401646622},
{"learn":[3.258108469],"iteration":853,"passed_time":0.814334091,"remaining_time":0.1392187088},
{"learn":[3.256424936],"iteration":854,"passed_time":0.8153132205,"remaining_time":0.1382694935},
{"learn":[3.254817983],"iteration":855,"passed_time":0.8162176731,"remaining_time":0.1373076459},
{"learn":[3.253898449],"iteration":856,"passed_time":0.8170716781,"remaining_time":0.1363375145},
{"learn":[3.253023652],"iteration":857,"passed_time":0.8178696715,"remaining_time":0.1353583839},
{"learn":[3.252845542],"iteration":858,"passed_time":0.8188681401,"remaining_time":0.1344125818},
{"learn":[3.252316026],"iteration":859,"passed_time":0.820089066,"remaining_time":0.1335028712},
{"learn":[3.24975301],"iteration":860,"passed_time":0.8210787228,"remaining_time":0.1325551016},
{"learn":[3.249151075],"iteration":861,"passed_time":0.8219635522,"remaining_time":0.1315904527},
{"learn":[3.246257135],"iteration":862,"passed_time":0.8230822978,"remaining_time":0.1306631226},
{"learn":[3.243826471],"iteration":863,"passed_time":0.8243503305,"remaining_time":0.1297588483},
{"learn":[3.243190653],"iteration":864,"passed_time":0.825468588,"remaining_time":0.1288303577},
{"learn":[3.24008797],"iteration":865,"passed_time":0.8265174172,"remaining_time":0.1278906858},
{"learn":[3.240036811],"iteration":866,"passed_time":0.8273521447,"remaining_time":0.1269179184},
{"learn":[3.238676314],"iteration":867,"passed_time":0.82823598,"remaining_time":0.1259529371},
{"learn":[3.237848782],"iteration":868,"passed_time":0.8291230277,"remaining_time":0.1249886267},
{"learn":[3.236405498],"iteration":869,"passed_time":0.8298537531,"remaining_time":0.1240011355},
{"learn":[3.233378068],"iteration":870,"passed_time":0.8306356676,"remaining_time":0.1230218153},
{"learn":[3.233169169],"iteration":871,"passed_time":0.8314000638,"remaining_time":0.1220403763},
{"learn":[3.232434885],"iteration":872,"passed_time":0.8322117426,"remaining_time":0.1210663131},
{"learn":[3.229978115],"iteration":873,"passed_time":0.832989847,"remaining_time":0.1200877811},
{"learn":[3.229648848],"iteration":874,"passed_time":0.8339307233,"remaining_time":0.1191329605},
{"learn":[3.227208761],"iteration":875,"passed_time":0.8353958189,"remaining_time":0.1182523762},
{"learn":[3.226258869],"iteration":876,"passed_time":0.8363065821,"remaining_time":0.1172927133},
{"learn":[3.225331995],"iteration":877,"passed_time":0.837248548,"remaining_time":0.1163374976},
{"learn":[3.221968268],"iteration":878,"passed_time":0.8380392028,"remaining_time":0.115361483},
{"learn":[3.221166317],"iteration":879,"passed_time":0.8389121028,"remaining_time":0.1143971049},
{"learn":[3.220047503],"iteration":880,"passed_time":0.8397275119,"remaining_time":0.113425169},
{"learn":[3.21982781],"iteration":881,"passed_time":0.8405794349,"remaining_time":0.1124584732},
{"learn":[3.216693405],"iteration":882,"passed_time":0.841412752,"remaining_time":0.1114895719},
{"learn":[3.214798761],"iteration":883,"passed_time":0.8423374401,"remaining_time":0.1105329673},
{"learn":[3.214395085],"iteration":884,"passed_time":0.8431800209,"remaining_time":0.1095657654},
{"learn":[3.213470696],"iteration":885,"passed_time":0.844002264,"remaining_time":0.1085962281},
{"learn":[3.211595017],"iteration":886,"passed_time":0.8449167663,"remaining_time":0.1076387763},
{"learn":[3.210965255],"iteration":887,"passed_time":0.8458613106,"remaining_time":0.1066852104},
{"learn":[3.209413583],"iteration":888,"passed_time":0.8466981716,"remaining_time":0.1057182194},
{"learn":[3.208331683],"iteration":889,"passed_time":0.847497305,"remaining_time":0.1047468579},
{"learn":[3.207110711],"iteration":890,"passed_time":0.8485025651,"remaining_time":0.1038010994},
{"learn":[3.204519413],"iteration":891,"passed_time":0.8494731271,"remaining_time":0.1028510064},
{"learn":[3.201421296],"iteration":892,"passed_time":0.8507801201,"remaining_time":0.101941179},
{"learn":[3.200691259],"iteration":893,"passed_time":0.851690118,"remaining_time":0.1009833921},
{"learn":[3.200485067],"iteration":894,"passed_time":0.8525720482,"remaining_time":0.1000224191},
{"learn":[3.197467568],"iteration":895,"passed_time":0.853402732,"remaining_time":0.09905567425},
{"learn":[3.195838544],"iteration":896,"passed_time":0.8543517276,"remaining_time":0.09810281821},
{"learn":[3.195671746],"iteration":897,"passed_time":0.855219511,"remaining_time":0.09714074623},
{"learn":[3.194213094],"iteration":898,"passed_time":0.8561059027,"remaining_time":0.09618097461},
{"learn":[3.192884691],"iteration":899,"passed_time":0.856901692,"remaining_time":0.09521129911},
{"learn":[3.188364239],"iteration":900,"passed_time":0.8578167654,"remaining_time":0.09425511629},
{"learn":[3.185219478],"iteration":901,"passed_time":0.858566466,"remaining_time":0.09328105728},
{"learn":[3.184120387],"iteration":902,"passed_time":0.8593373248,"remaining_time":0.092309768},
{"learn":[3.183725321],"iteration":903,"passed_time":0.8600988716,"remaining_time":0.09133793327},
{"learn":[3.181264554],"iteration":904,"passed_time":0.8609365684,"remaining_time":0.09037455691},
{"learn":[3.180741589],"iteration":905,"passed_time":0.8618098236,"remaining_time":0.08941514727},
{"learn":[3.179782639],"iteration":906,"passed_time":0.8626718432,"remaining_time":0.08845477554},
{"learn":[3.176377564],"iteration":907,"passed_time":0.8635583097,"remaining_time":0.08749709746},
{"learn":[3.174078182],"iteration":908,"passed_time":0.8653939998,"remaining_time":0.08663460284},
{"learn":[3.171242379],"iteration":909,"passed_time":0.8663029696,"remaining_time":0.08567831568},
{"learn":[3.170421012],"iteration":910,"passed_time":0.8671847557,"remaining_time":0.08471947668},
{"learn":[3.170087224],"iteration":911,"passed_time":0.8679574547,"remaining_time":0.08375028072},
{"learn":[3.167303059],"iteration":912,"passed_time":0.8687795503,"remaining_time":0.08278622221},
{"learn":[3.16705966],"iteration":913,"passed_time":0.8695988074,"remaining_time":0.08182220727},
{"learn":[3.165667683],"iteration":914,"passed_time":0.8707578529,"remaining_time":0.08089007376},
{"learn":[3.164689733],"iteration":915,"passed_time":0.871836409,"remaining_time":0.07995006371},
{"learn":[3.163311455],"iteration":916,"passed_time":0.8728437403,"remaining_time":0.07900330474},
{"learn":[3.159425016],"iteration":917,"passed_time":0.8736750286,"remaining_time":0.07804068883},
{"learn":[3.159327058],"iteration":918,"passed_time":0.8744601484,"remaining_time":0.07707428947},
{"learn":[3.15819426],"iteration":919,"passed_time":0.8752573177,"remaining_time":0.07610933197},
{"learn":[3.157086603],"iteration":920,"passed_time":0.8761625446,"remaining_time":0.07515400763},
{"learn":[3.153354154],"iteration":921,"passed_time":0.8769442219,"remaining_time":0.07418833982},
{"learn":[3.153261317],"iteration":922,"passed_time":0.8776107879,"remaining_time":0.07321346768},
{"learn":[3.153168454],"iteration":923,"passed_time":0.8783272435,"remaining_time":0.07224336635},
{"learn":[3.152080399],"iteration":924,"passed_time":0.879078963,"remaining_time":0.07127667268},
{"learn":[3.151635144],"iteration":925,"passed_time":0.8802445246,"remaining_time":0.07034351492},
{"learn":[3.147762655],"iteration":926,"passed_time":0.8813780081,"remaining_time":0.06940732966},
{"learn":[3.147172317],"iteration":927,"passed_time":0.8821031159,"remaining_time":0.06843903486},
{"learn":[3.146254125],"iteration":928,"passed_time":0.8827791811,"remaining_time":0.06746751545},
{"learn":[3.144869828],"iteration":929,"passed_time":0.8834931231,"remaining_time":0.06649948238},
{"learn":[3.143466218],"iteration":930,"passed_time":0.8841936244,"remaining_time":0.06553099902},
{"learn":[3.141919643],"iteration":931,"passed_time":0.8848467223,"remaining_time":0.0645596321},
{"learn":[3.141054135],"iteration":932,"passed_time":0.8854528031,"remaining_time":0.06358557107},
{"learn":[3.139390417],"iteration":933,"passed_time":0.8861748689,"remaining_time":0.06262049395},
{"learn":[3.139025283],"iteration":934,"passed_time":0.8868420526,"remaining_time":0.0616521213},
{"learn":[3.137824183],"iteration":935,"passed_time":0.8874784235,"remaining_time":0.06068228537},
{"learn":[3.135620453],"iteration":936,"passed_time":0.8881338818,"remaining_time":0.05971444456},
{"learn":[3.13443178],"iteration":937,"passed_time":0.8887969795,"remaining_time":0.05874777476},
{"learn":[3.132765713],"iteration":938,"passed_time":0.8894159571,"remaining_time":0.05777888539},
{"learn":[3.131434124],"iteration":939,"passed_time":0.890168679,"remaining_time":0.05681927738},
{"learn":[3.128384262],"iteration":940,"passed_time":0.8908581641,"remaining_time":0.05585614419},
{"learn":[3.128120455],"iteration":941,"passed_time":0.8915372015,"remaining_time":0.05489294871},
{"learn":[3.126314615],"iteration":942,"passed_time":0.8922161933,"remaining_time":0.05393035315},
{"learn":[3.125409666],"iteration":943,"passed_time":0.8928698246,"remaining_time":0.052966854},
{"learn":[3.123072589],"iteration":944,"passed_time":0.8935080644,"remaining_time":0.05200311486},
{"learn":[3.122921099],"iteration":945,"passed_time":0.8941474658,"remaining_time":0.05104013018},
{"learn":[3.122182662],"iteration":946,"passed_time":0.8950320094,"remaining_time":0.05009154857},
{"learn":[3.120040951],"iteration":947,"passed_time":0.8961449957,"remaining_time":0.04915563267},
{"learn":[3.118767799],"iteration":948,"passed_time":0.8968647642,"remaining_time":0.04819821178},
{"learn":[3.118203218],"iteration":949,"passed_time":0.8975290732,"remaining_time":0.04723837228},
{"learn":[3.116343362],"iteration":950,"passed_time":0.8983454599,"remaining_time":0.04628699004},
{"learn":[3.11480829],"iteration":951,"passed_time":0.8990097037,"remaining_time":0.04532822035},
{"learn":[3.112607903],"iteration":952,"passed_time":0.8997331382,"remaining_time":0.04437298793},
{"learn":[3.111661241],"iteration":953,"passed_time":0.9004547782,"remaining_time":0.04341815492},
{"learn":[3.110249676],"iteration":954,"passed_time":0.9011210085,"remaining_time":0.04246119935},
{"learn":[3.107333579],"iteration":955,"passed_time":0.9018738176,"remaining_time":0.04150883679},
{"learn":[3.107149851],"iteration":956,"passed_time":0.9025710787,"remaining_time":0.04055439539},
{"learn":[3.106867336],"iteration":957,"passed_time":0.903247217,"remaining_time":0.03959956484},
{"learn":[3.10364681],"iteration":958,"passed_time":0.9040142158,"remaining_time":0.03864920005},
{"learn":[3.102703811],"iteration":959,"passed_time":0.9047592945,"remaining_time":0.03769830394},
{"learn":[3.101469264],"iteration":960,"passed_time":0.9055012868,"remaining_time":0.03674771091},
{"learn":[3.09863569],"iteration":961,"passed_time":0.9062281027,"remaining_time":0.03579695208},
{"learn":[3.09645939],"iteration":962,"passed_time":0.9068946276,"remaining_time":0.03484434187},
{"learn":[3.096240186],"iteration":963,"passed_time":0.9075709603,"remaining_time":0.03389269146},
{"learn":[3.094838828],"iteration":964,"passed_time":0.9082850938,"remaining_time":0.03294298268},
{"learn":[3.094176802],"iteration":965,"passed_time":0.9090806408,"remaining_time":0.03199662711},
{"learn":[3.093182279],"iteration":966,"passed_time":0.9098898554,"remaining_time":0.03105104987},
{"learn":[3.090150687],"iteration":967,"passed_time":0.9111408077,"remaining_time":0.03012035728},
{"learn":[3.088612829],"iteration":968,"passed_time":0.911978556,"remaining_time":0.02917578456},
{"learn":[3.087153684],"iteration":969,"passed_time":0.9128661657,"remaining_time":0.0282329742},
{"learn":[3.085866843],"iteration":970,"passed_time":0.9135897876,"remaining_time":0.02728537986},
{"learn":[3.082669094],"iteration":971,"passed_time":0.9142508606,"remaining_time":0.02633644454},
{"learn":[3.081047548],"iteration":972,"passed_time":0.9148713604,"remaining_time":0.02538697506},
{"learn":[3.079684322],"iteration":973,"passed_time":0.9154943467,"remaining_time":0.02443824745},
{"learn":[3.07613431],"iteration":974,"passed_time":0.9161380576,"remaining_time":0.02349071943},
{"learn":[3.074005935],"iteration":975,"passed_time":0.9167828543,"remaining_time":0.02254384068},
{"learn":[3.072988853],"iteration":976,"passed_time":0.9174014573,"remaining_time":0.02159696368},
{"learn":[3.072344268],"iteration":977,"passed_time":0.9181424916,"remaining_time":0.02065351208},
{"learn":[3.070654438],"iteration":978,"passed_time":0.9188251535,"remaining_time":0.01970922188},
{"learn":[3.069724506],"iteration":979,"passed_time":0.9195205432,"remaining_time":0.01876572537},
{"learn":[3.067763166],"iteration":980,"passed_time":0.9201545039,"remaining_time":0.01782154493},
{"learn":[3.066737893],"iteration":981,"passed_time":0.9209125967,"remaining_time":0.01688027163},
{"learn":[3.065248174],"iteration":982,"passed_time":0.9216241214,"remaining_time":0.01593856568},
{"learn":[3.063186837],"iteration":983,"passed_time":0.9223971494,"remaining_time":0.01499832763},
{"learn":[3.062880371],"iteration":984,"passed_time":0.923184954,"remaining_time":0.01405865412},
{"learn":[3.061288645],"iteration":985,"passed_time":0.9240056763,"remaining_time":0.01311975605},
{"learn":[3.059970575],"iteration":986,"passed_time":0.924776523,"remaining_time":0.01218044053},
{"learn":[3.059576341],"iteration":987,"passed_time":0.9261308617,"remaining_time":0.01124855298},
{"learn":[3.058175919],"iteration":988,"passed_time":0.9272032228,"remaining_time":0.01031267487},
{"learn":[3.056830702],"iteration":989,"passed_time":0.9279638691,"remaining_time":0.009373372415},
{"learn":[3.056336579],"iteration":990,"passed_time":0.9287289308,"remaining_time":0.008434470612},
{"learn":[3.055810414],"iteration":991,"passed_time":0.9295066031,"remaining_time":0.007496020993},
{"learn":[3.055476518],"iteration":992,"passed_time":0.9304755342,"remaining_time":0.006559243443},
{"learn":[3.053331734],"iteration":993,"passed_time":0.9317618472,"remaining_time":0.005624316985},
{"learn":[3.050890374],"iteration":994,"passed_time":0.9327362804,"remaining_time":0.004687116987},
{"learn":[3.04972623],"iteration":995,"passed_time":0.9335377031,"remaining_time":0.003749147402},
{"learn":[3.047217327],"iteration":996,"passed_time":0.9343620668,"remaining_time":0.002811520763},
{"learn":[3.047155483],"iteration":997,"passed_time":0.9350238236,"remaining_time":0.001873795238},
{"learn":[3.04430671],"iteration":998,"passed_time":0.9357416995,"remaining_time":0.0009366783779},
{"learn":[3.042664195],"iteration":999,"passed_time":0.936508351,"remaining_time":0}
]}